{
  "year": 2025,
  "generatedAt": "2026-04-07T07:08:28.477950",
  "investors": {
    "08171496-3b33-4029-ad4b-2afc4f6fdf82": {
      "name": "Jacob Alsup",
      "totalDeals2025": 55,
      "mlsDeals2025": 32,
      "offMarketDeals2025": 23,
      "rebuiltDeals2025": 1,
      "mlsRate": 0.5818,
      "recorderVolume2025": 8584872,
      "estMlsVolume2025": 4994834.62,
      "estCommission3pct": 149845.04,
      "opportunityType": "MLS-Heavy"
    },
    "28c5611b-3ddf-4166-9355-2840903ab352": {
      "name": "Camren Berry",
      "totalDeals2025": 14,
      "mlsDeals2025": 0,
      "offMarketDeals2025": 14,
      "rebuiltDeals2025": 1,
      "mlsRate": 0.0,
      "recorderVolume2025": 3738000,
      "estMlsVolume2025": 0.0,
      "estCommission3pct": 0.0,
      "opportunityType": "Off-Market"
    },
    "5783950c-8e88-42ee-958e-b6d084ba45f3": {
      "name": "Adam Hobson",
      "totalDeals2025": 29,
      "mlsDeals2025": 0,
      "offMarketDeals2025": 29,
      "rebuiltDeals2025": 2,
      "mlsRate": 0.0,
      "recorderVolume2025": 2602053,
      "estMlsVolume2025": 0.0,
      "estCommission3pct": 0.0,
      "opportunityType": "Off-Market"
    },
    "d03f809d-cdde-4161-86d7-a497543568af": {
      "name": "Zac Peterson",
      "totalDeals2025": 17,
      "mlsDeals2025": 5,
      "offMarketDeals2025": 12,
      "rebuiltDeals2025": 1,
      "mlsRate": 0.2941,
      "recorderVolume2025": 2505500,
      "estMlsVolume2025": 736911.76,
      "estCommission3pct": 22107.35,
      "opportunityType": "Mixed"
    },
    "abb5cccb-f5e0-401a-9a45-b98d26b667bd": {
      "name": "Will Moorehead",
      "totalDeals2025": 5,
      "mlsDeals2025": 2,
      "offMarketDeals2025": 3,
      "rebuiltDeals2025": 0,
      "mlsRate": 0.4,
      "recorderVolume2025": 2395683,
      "estMlsVolume2025": 958273.2,
      "estCommission3pct": 28748.2,
      "opportunityType": "Mixed"
    },
    "46d3392c-c2da-4feb-98ef-0095f6562438": {
      "name": "Mike Wehby",
      "totalDeals2025": 22,
      "mlsDeals2025": 11,
      "offMarketDeals2025": 11,
      "rebuiltDeals2025": 2,
      "mlsRate": 0.5,
      "recorderVolume2025": 2374087,
      "estMlsVolume2025": 1187043.5,
      "estCommission3pct": 35611.31,
      "opportunityType": "MLS-Heavy"
    },
    "412a9845-9862-41dd-a81d-717c7591b611": {
      "name": "Kenny Shaw International Immobiliare LLC",
      "totalDeals2025": 29,
      "mlsDeals2025": 1,
      "offMarketDeals2025": 28,
      "rebuiltDeals2025": 5,
      "mlsRate": 0.0345,
      "recorderVolume2025": 2356650,
      "estMlsVolume2025": 81263.79,
      "estCommission3pct": 2437.91,
      "opportunityType": "Off-Market"
    },
    "2e7f2a51-8c24-4095-9500-1b95d3b4a88b": {
      "name": "Todd Simpson",
      "totalDeals2025": 15,
      "mlsDeals2025": 7,
      "offMarketDeals2025": 8,
      "rebuiltDeals2025": 1,
      "mlsRate": 0.4667,
      "recorderVolume2025": 1357915,
      "estMlsVolume2025": 633693.67,
      "estCommission3pct": 19010.81,
      "opportunityType": "Mixed"
    },
    "6c511c31-dbf6-4d87-af37-d1b93107386a": {
      "name": "Josh Handler",
      "totalDeals2025": 11,
      "mlsDeals2025": 2,
      "offMarketDeals2025": 9,
      "rebuiltDeals2025": 1,
      "mlsRate": 0.1818,
      "recorderVolume2025": 1294522,
      "estMlsVolume2025": 235367.64,
      "estCommission3pct": 7061.03,
      "opportunityType": "Off-Market"
    },
    "6e860470-1ef0-4bb2-9bf4-a0799bd1fe46": {
      "name": "Tanner Dillard",
      "totalDeals2025": 11,
      "mlsDeals2025": 5,
      "offMarketDeals2025": 6,
      "rebuiltDeals2025": 1,
      "mlsRate": 0.4545,
      "recorderVolume2025": 968500,
      "estMlsVolume2025": 440227.27,
      "estCommission3pct": 13206.82,
      "opportunityType": "Mixed"
    },
    "10697af8-0636-4863-983b-1fe7723c5001": {
      "name": "Ray Rangoonwala",
      "totalDeals2025": 8,
      "mlsDeals2025": 4,
      "offMarketDeals2025": 4,
      "rebuiltDeals2025": 2,
      "mlsRate": 0.5,
      "recorderVolume2025": 951500,
      "estMlsVolume2025": 475750.0,
      "estCommission3pct": 14272.5,
      "opportunityType": "MLS-Heavy"
    },
    "f8b581c8-78cf-4742-89e7-ab57cdfa0e98": {
      "name": "Brie King",
      "totalDeals2025": 3,
      "mlsDeals2025": 2,
      "offMarketDeals2025": 1,
      "rebuiltDeals2025": 0,
      "mlsRate": 0.6667,
      "recorderVolume2025": 942848,
      "estMlsVolume2025": 628565.33,
      "estCommission3pct": 18856.96,
      "opportunityType": "MLS-Heavy"
    },
    "6a776e76-1c34-4e40-9201-56d818d83faa": {
      "name": "Adam Hatton",
      "totalDeals2025": 2,
      "mlsDeals2025": 1,
      "offMarketDeals2025": 1,
      "rebuiltDeals2025": 1,
      "mlsRate": 0.5,
      "recorderVolume2025": 300000,
      "estMlsVolume2025": 150000.0,
      "estCommission3pct": 4500.0,
      "opportunityType": "MLS-Heavy"
    },
    "a233f4ef-79a1-4c5e-a908-69d19b043a21": {
      "name": "Brad Phillips",
      "totalDeals2025": 5,
      "mlsDeals2025": 1,
      "offMarketDeals2025": 4,
      "rebuiltDeals2025": 1,
      "mlsRate": 0.2,
      "recorderVolume2025": 240700,
      "estMlsVolume2025": 48140.0,
      "estCommission3pct": 1444.2,
      "opportunityType": "Mixed"
    },
    "422be436-6d7b-42f0-80be-67e7e4a6f89c": {
      "name": "Alan MacGavin",
      "totalDeals2025": 3,
      "mlsDeals2025": 2,
      "offMarketDeals2025": 1,
      "rebuiltDeals2025": 0,
      "mlsRate": 0.6667,
      "recorderVolume2025": 220000,
      "estMlsVolume2025": 146666.67,
      "estCommission3pct": 4400.0,
      "opportunityType": "MLS-Heavy"
    },
    "4579c0d8-b5dd-4c28-b34e-a1c1da84bf99": {
      "name": "Prime Estate Holdings LLC",
      "totalDeals2025": 1,
      "mlsDeals2025": 1,
      "offMarketDeals2025": 0,
      "rebuiltDeals2025": 0,
      "mlsRate": 1.0,
      "recorderVolume2025": 205000,
      "estMlsVolume2025": 205000.0,
      "estCommission3pct": 6150.0,
      "opportunityType": "MLS-Heavy"
    },
    "4038ad1f-6d48-458a-906b-4557d479bd76": {
      "name": "Kimble Brooks",
      "totalDeals2025": 4,
      "mlsDeals2025": 1,
      "offMarketDeals2025": 3,
      "rebuiltDeals2025": 1,
      "mlsRate": 0.25,
      "recorderVolume2025": 194000,
      "estMlsVolume2025": 48500.0,
      "estCommission3pct": 1455.0,
      "opportunityType": "Mixed"
    },
    "01961707-df37-73c7-82c4-74ca392400ab": {
      "name": "Tony Wallace",
      "totalDeals2025": 6,
      "mlsDeals2025": 0,
      "offMarketDeals2025": 6,
      "rebuiltDeals2025": 3,
      "mlsRate": 0.0,
      "recorderVolume2025": 127000,
      "estMlsVolume2025": 0.0,
      "estCommission3pct": 0.0,
      "opportunityType": "Off-Market"
    },
    "0195f44b-0707-791c-bb4f-20b330bef893": {
      "name": "Mark Hutter",
      "totalDeals2025": 3,
      "mlsDeals2025": 1,
      "offMarketDeals2025": 2,
      "rebuiltDeals2025": 3,
      "mlsRate": 0.3333,
      "recorderVolume2025": 81750,
      "estMlsVolume2025": 27250.0,
      "estCommission3pct": 817.5,
      "opportunityType": "Mixed"
    },
    "36cf2b58-aa79-4cb0-adda-eb525c55f866": {
      "name": "Ross Nazari",
      "totalDeals2025": 9,
      "mlsDeals2025": 2,
      "offMarketDeals2025": 7,
      "rebuiltDeals2025": 4,
      "mlsRate": 0.2222,
      "recorderVolume2025": 59000,
      "estMlsVolume2025": 13111.11,
      "estCommission3pct": 393.33,
      "opportunityType": "Mixed"
    },
    "9effe7ef-0c35-43a8-aa9c-70cd51d9aee5": {
      "name": "PHIL DUKE",
      "totalDeals2025": 2,
      "mlsDeals2025": 1,
      "offMarketDeals2025": 1,
      "rebuiltDeals2025": 0,
      "mlsRate": 0.5,
      "recorderVolume2025": 46500,
      "estMlsVolume2025": 23250.0,
      "estCommission3pct": 697.5,
      "opportunityType": "MLS-Heavy"
    },
    "1d3eb9bd-a9fc-4b8b-bb35-c7bbaa204288": {
      "name": "Robert Rivera",
      "totalDeals2025": 1,
      "mlsDeals2025": 1,
      "offMarketDeals2025": 0,
      "rebuiltDeals2025": 2,
      "mlsRate": 1.0,
      "recorderVolume2025": 41000,
      "estMlsVolume2025": 41000.0,
      "estCommission3pct": 1230.0,
      "opportunityType": "MLS-Heavy"
    },
    "35ca761e-94cc-499c-832b-dcebcd53e530": {
      "name": "Steven Lane",
      "totalDeals2025": 2,
      "mlsDeals2025": 2,
      "offMarketDeals2025": 0,
      "rebuiltDeals2025": 0,
      "mlsRate": 1.0,
      "recorderVolume2025": 10000,
      "estMlsVolume2025": 10000.0,
      "estCommission3pct": 300.0,
      "opportunityType": "MLS-Heavy"
    },
    "0197c860-79ae-7496-aa9a-96389642c59e": {
      "name": "David Labib",
      "totalDeals2025": 2,
      "mlsDeals2025": 1,
      "offMarketDeals2025": 1,
      "rebuiltDeals2025": 3,
      "mlsRate": 0.5,
      "recorderVolume2025": 0,
      "estMlsVolume2025": 0.0,
      "estCommission3pct": 0.0,
      "opportunityType": "MLS-Heavy"
    },
    "7beb8c08-6edb-410c-9ad0-b51eea81a7ae": {
      "name": "Ethan Adler",
      "totalDeals2025": 1,
      "mlsDeals2025": 0,
      "offMarketDeals2025": 1,
      "rebuiltDeals2025": 1,
      "mlsRate": 0.0,
      "recorderVolume2025": 0,
      "estMlsVolume2025": 0.0,
      "estCommission3pct": 0.0,
      "opportunityType": "Off-Market"
    }
  },
  "totals": {
    "totalDeals": 260,
    "mlsDeals": 85,
    "recorderVolume": 31597080,
    "estMlsVolume": 11084848.56,
    "estCommission": 332545.46
  }
}