{
  "investor": {
    "id": "01977f05-7a96-7182-b141-e986e254106f",
    "name": "Janice Shearin",
    "email": "Jdrealestategroup@yahoo.com",
    "phone": "+1 (252) 326-1197",
    "totalWon": 1,
    "totalBids": 11,
    "ytdWon": 0,
    "ytdBids": 6,
    "entities": [
      "J & D REAL ESTATE GROUP LLC"
    ]
  },
  "stats": {
    "totalTransactions2025": 11,
    "rebuiltTransactions": 0,
    "recorderTransactions": 19,
    "quarterlyStats": {
      "2025-Q1": {
        "rebuilt": 0,
        "total": 2
      },
      "2025-Q2": {
        "rebuilt": 0,
        "total": 0
      },
      "2025-Q3": {
        "rebuilt": 0,
        "total": 9
      },
      "2025-Q4": {
        "rebuilt": 0,
        "total": 0
      },
      "2026-Q1": {
        "rebuilt": 0,
        "total": 8
      }
    }
  },
  "properties": [
    {
      "propertyId": null,
      "attomId": 303215724,
      "offerDate": "2026-03-06T06:00:00.000Z",
      "offerPrice": 50000,
      "status": "recorded",
      "isRebuilt": false,
      "address": "1004 VANCE ST, ROANOKE RAPIDS NC",
      "city": "ROANOKE RAPIDS",
      "state": "NC",
      "beds": 4,
      "baths": 2,
      "sqft": 1504,
      "lotSize": 0.1960055,
      "lat": 36.457918,
      "lng": -77.663834,
      "entity": "J & D REAL ESTATE GROUP LLC"
    },
    {
      "propertyId": null,
      "attomId": 177740603,
      "offerDate": "2026-02-20T06:00:00.000Z",
      "offerPrice": 25000,
      "status": "recorded",
      "isRebuilt": false,
      "address": "5603 ROSLYN RD, DURHAM NC",
      "city": "DURHAM",
      "state": "NC",
      "beds": 0,
      "baths": null,
      "sqft": 0,
      "lotSize": 0.5100092,
      "lat": 36.095661,
      "lng": -78.898481,
      "entity": "J & D REAL ESTATE GROUP LLC"
    },
    {
      "propertyId": null,
      "attomId": 177740610,
      "offerDate": "2026-02-20T06:00:00.000Z",
      "offerPrice": 25000,
      "status": "recorded",
      "isRebuilt": false,
      "address": "5719 ROSLYN RD, DURHAM NC",
      "city": "DURHAM",
      "state": "NC",
      "beds": 0,
      "baths": null,
      "sqft": 0,
      "lotSize": 0.5399908,
      "lat": 36.098297,
      "lng": -78.898577,
      "entity": "J & D REAL ESTATE GROUP LLC"
    },
    {
      "propertyId": null,
      "attomId": 177740608,
      "offerDate": "2026-02-20T06:00:00.000Z",
      "offerPrice": 25000,
      "status": "recorded",
      "isRebuilt": false,
      "address": "5711 ROSLYN RD, DURHAM NC",
      "city": "DURHAM",
      "state": "NC",
      "beds": 0,
      "baths": null,
      "sqft": 0,
      "lotSize": 0.5100092,
      "lat": 36.097748,
      "lng": -78.898545,
      "entity": "J & D REAL ESTATE GROUP LLC"
    },
    {
      "propertyId": null,
      "attomId": 177740609,
      "offerDate": "2026-02-20T06:00:00.000Z",
      "offerPrice": 25000,
      "status": "recorded",
      "isRebuilt": false,
      "address": "5715 ROSLYN RD, DURHAM NC",
      "city": "DURHAM",
      "state": "NC",
      "beds": 0,
      "baths": null,
      "sqft": 0,
      "lotSize": 0.5199954,
      "lat": 36.098023,
      "lng": -78.898561,
      "entity": "J & D REAL ESTATE GROUP LLC"
    },
    {
      "propertyId": null,
      "attomId": 177740607,
      "offerDate": "2026-02-20T06:00:00.000Z",
      "offerPrice": 25000,
      "status": "recorded",
      "isRebuilt": false,
      "address": "5707 ROSLYN RD, DURHAM NC",
      "city": "DURHAM",
      "state": "NC",
      "beds": 0,
      "baths": null,
      "sqft": 0,
      "lotSize": 0.5100092,
      "lat": 36.097473,
      "lng": -78.898532,
      "entity": "J & D REAL ESTATE GROUP LLC"
    },
    {
      "propertyId": null,
      "attomId": 177740611,
      "offerDate": "2026-02-20T06:00:00.000Z",
      "offerPrice": 25000,
      "status": "recorded",
      "isRebuilt": false,
      "address": "5723 ROSLYN RD, DURHAM NC",
      "city": "DURHAM",
      "state": "NC",
      "beds": 0,
      "baths": null,
      "sqft": 0,
      "lotSize": 0.7,
      "lat": 36.098615,
      "lng": -78.898596,
      "entity": "J & D REAL ESTATE GROUP LLC"
    },
    {
      "propertyId": null,
      "attomId": 177740602,
      "offerDate": "2026-02-20T06:00:00.000Z",
      "offerPrice": 25000,
      "status": "recorded",
      "isRebuilt": false,
      "address": "5521 ROSLYN RD, DURHAM NC",
      "city": "DURHAM",
      "state": "NC",
      "beds": 0,
      "baths": null,
      "sqft": 0,
      "lotSize": 0.5199954,
      "lat": 36.095386,
      "lng": -78.898474,
      "entity": "J & D REAL ESTATE GROUP LLC"
    },
    {
      "propertyId": null,
      "attomId": 303240039,
      "offerDate": "2025-09-24T05:00:00.000Z",
      "offerPrice": 0,
      "status": "recorded",
      "isRebuilt": false,
      "address": "405 CHURCH ST E, AHOSKIE NC",
      "city": "AHOSKIE",
      "state": "NC",
      "beds": 4,
      "baths": 2,
      "sqft": 620,
      "lotSize": 0.0600092,
      "lat": 36.283088,
      "lng": -76.9831,
      "entity": "J & D REAL ESTATE GROUP LLC"
    },
    {
      "propertyId": null,
      "attomId": 303240099,
      "offerDate": "2025-09-24T05:00:00.000Z",
      "offerPrice": 0,
      "status": "recorded",
      "isRebuilt": false,
      "address": "115 DR MARTIN LUTHER KING JR DR S, AHOSKIE NC",
      "city": "AHOSKIE",
      "state": "NC",
      "beds": 2,
      "baths": 2,
      "sqft": 1325,
      "lotSize": 0.1,
      "lat": 36.283303,
      "lng": -76.982999,
      "entity": "J & D REAL ESTATE GROUP LLC"
    },
    {
      "propertyId": null,
      "attomId": 303240046,
      "offerDate": "2025-09-24T05:00:00.000Z",
      "offerPrice": 0,
      "status": "recorded",
      "isRebuilt": false,
      "address": "415 CHURCH ST E APT C, AHOSKIE NC",
      "city": "AHOSKIE",
      "state": "NC",
      "beds": 0,
      "baths": 3,
      "sqft": 1277,
      "lotSize": 0.2600092,
      "lat": 36.282979,
      "lng": -76.98266,
      "entity": "J & D REAL ESTATE GROUP LLC"
    },
    {
      "propertyId": null,
      "attomId": 303240098,
      "offerDate": "2025-09-24T05:00:00.000Z",
      "offerPrice": 0,
      "status": "recorded",
      "isRebuilt": false,
      "address": "403 CHURCH ST E, AHOSKIE NC",
      "city": "AHOSKIE",
      "state": "NC",
      "beds": 4,
      "baths": 2,
      "sqft": 840,
      "lotSize": 0.0800046,
      "lat": 36.283163,
      "lng": -76.983166,
      "entity": "J & D REAL ESTATE GROUP LLC"
    },
    {
      "propertyId": null,
      "attomId": 303240107,
      "offerDate": "2025-09-24T05:00:00.000Z",
      "offerPrice": 0,
      "status": "recorded",
      "isRebuilt": false,
      "address": "107 DR MARTIN LUTHER KING JR DR S, AHOSKIE NC",
      "city": "AHOSKIE",
      "state": "NC",
      "beds": 0,
      "baths": 1,
      "sqft": 1145,
      "lotSize": 0.0800046,
      "lat": 36.283527,
      "lng": -76.982819,
      "entity": "J & D REAL ESTATE GROUP LLC"
    },
    {
      "propertyId": null,
      "attomId": 303240106,
      "offerDate": "2025-09-24T05:00:00.000Z",
      "offerPrice": 0,
      "status": "recorded",
      "isRebuilt": false,
      "address": "111 DR MARTIN LUTHER KING JR DR S, AHOSKIE NC",
      "city": "AHOSKIE",
      "state": "NC",
      "beds": 2,
      "baths": 1,
      "sqft": 1201,
      "lotSize": 0.0699954,
      "lat": 36.283424,
      "lng": -76.982902,
      "entity": "J & D REAL ESTATE GROUP LLC"
    },
    {
      "propertyId": null,
      "attomId": 234065795,
      "offerDate": "2025-07-11T05:00:00.000Z",
      "offerPrice": 140000,
      "status": "recorded",
      "isRebuilt": false,
      "address": "300 WAGRAM ST, LAURINBURG NC",
      "city": "LAURINBURG",
      "state": "NC",
      "beds": 6,
      "baths": 2,
      "sqft": 1824,
      "lotSize": 0.2295684,
      "lat": 34.787136,
      "lng": -79.45087,
      "entity": "J & D REAL ESTATE GROUP LLC"
    },
    {
      "propertyId": null,
      "attomId": 210734699,
      "offerDate": "2025-07-11T05:00:00.000Z",
      "offerPrice": 140000,
      "status": "recorded",
      "isRebuilt": false,
      "address": "1108 ANNE ST, LAURINBURG NC",
      "city": "LAURINBURG",
      "state": "NC",
      "beds": 3,
      "baths": 1,
      "sqft": 981,
      "lotSize": 0.3443526,
      "lat": 34.786746,
      "lng": -79.450551,
      "entity": "J & D REAL ESTATE GROUP LLC"
    },
    {
      "propertyId": null,
      "attomId": 234065794,
      "offerDate": "2025-07-11T05:00:00.000Z",
      "offerPrice": 140000,
      "status": "recorded",
      "isRebuilt": false,
      "address": "304 WAGRAM ST, LAURINBURG NC",
      "city": "LAURINBURG",
      "state": "NC",
      "beds": 2,
      "baths": 1,
      "sqft": 1014,
      "lotSize": 0.3443526,
      "lat": 34.787357,
      "lng": -79.450623,
      "entity": "J & D REAL ESTATE GROUP LLC"
    },
    {
      "propertyId": null,
      "attomId": 303114171,
      "offerDate": "2025-03-14T05:00:00.000Z",
      "offerPrice": 18000,
      "status": "recorded",
      "isRebuilt": false,
      "address": "222 W 2ND AVE, CHADBOURN NC",
      "city": "CHADBOURN",
      "state": "NC",
      "beds": 0,
      "baths": null,
      "sqft": 0,
      "lotSize": 0,
      "lat": 34.324884,
      "lng": -78.828915,
      "entity": "J & D REAL ESTATE GROUP LLC"
    },
    {
      "propertyId": null,
      "attomId": 303197306,
      "offerDate": "2025-01-23T06:00:00.000Z",
      "offerPrice": 45000,
      "status": "recorded",
      "isRebuilt": false,
      "address": "16721 JUSTICE BRANCH RD, LITTLETON NC",
      "city": "LITTLETON",
      "state": "NC",
      "beds": 0,
      "baths": null,
      "sqft": 0,
      "lotSize": 12.5,
      "lat": 36.371299,
      "lng": -77.817867,
      "entity": "J & D REAL ESTATE GROUP LLC"
    }
  ]
}