{
  "investor": {
    "id": "19c1140e-4202-46df-83d5-295cb5ffbcc0",
    "name": "PCU LLC",
    "email": "bgp620@gmail.com",
    "phone": "+1 (205) 296-6953",
    "totalWon": 1,
    "totalBids": 1,
    "ytdWon": 0,
    "ytdBids": 0,
    "entities": [
      "MARUMA REAL ESTATE AL LLC"
    ]
  },
  "stats": {
    "totalTransactions2025": 111,
    "rebuiltTransactions": 0,
    "recorderTransactions": 188,
    "quarterlyStats": {
      "2025-Q1": {
        "rebuilt": 0,
        "total": 28
      },
      "2025-Q2": {
        "rebuilt": 0,
        "total": 28
      },
      "2025-Q3": {
        "rebuilt": 0,
        "total": 34
      },
      "2025-Q4": {
        "rebuilt": 0,
        "total": 21
      },
      "2026-Q1": {
        "rebuilt": 0,
        "total": 2
      }
    }
  },
  "properties": [
    {
      "propertyId": null,
      "attomId": 190087172,
      "offerDate": "2024-06-18",
      "offerPrice": 18000,
      "status": "recorder",
      "isRebuilt": false,
      "address": "2116 18TH WAY N, BESSEMER AL",
      "city": "BESSEMER",
      "state": "AL",
      "beds": null,
      "baths": null,
      "sqft": null,
      "lotSize": null,
      "lat": 33.414391,
      "lng": -86.978661
    },
    {
      "propertyId": null,
      "attomId": 144766479,
      "offerDate": "2024-06-06",
      "offerPrice": 77000,
      "status": "recorder",
      "isRebuilt": false,
      "address": "1232 FRISCO ST, BIRMINGHAM AL",
      "city": "BIRMINGHAM",
      "state": "AL",
      "beds": null,
      "baths": null,
      "sqft": null,
      "lotSize": null,
      "lat": 33.499796,
      "lng": -86.91923
    },
    {
      "propertyId": null,
      "attomId": 54780155,
      "offerDate": "2024-05-14",
      "offerPrice": 68500,
      "status": "recorder",
      "isRebuilt": false,
      "address": "4720 40TH PL N, BIRMINGHAM AL",
      "city": "BIRMINGHAM",
      "state": "AL",
      "beds": null,
      "baths": null,
      "sqft": null,
      "lotSize": null,
      "lat": 33.569764,
      "lng": -86.778687
    },
    {
      "propertyId": null,
      "attomId": 54536184,
      "offerDate": "2026-02-17",
      "offerPrice": 40000,
      "status": "recorder",
      "isRebuilt": false,
      "address": "7228 OPORTO MADRID BLVD S, BIRMINGHAM AL",
      "city": "BIRMINGHAM",
      "state": "AL",
      "beds": null,
      "baths": null,
      "sqft": null,
      "lotSize": null,
      "lat": 33.550608,
      "lng": -86.721065
    },
    {
      "propertyId": null,
      "attomId": 10808022,
      "offerDate": "2026-01-13",
      "offerPrice": 75000,
      "status": "recorder",
      "isRebuilt": false,
      "address": "1332 7TH PL NW, BIRMINGHAM AL",
      "city": "BIRMINGHAM",
      "state": "AL",
      "beds": null,
      "baths": null,
      "sqft": null,
      "lotSize": null,
      "lat": 33.621925,
      "lng": -86.708081
    },
    {
      "propertyId": null,
      "attomId": 144037380,
      "offerDate": "2025-12-30",
      "offerPrice": 16500,
      "status": "recorder",
      "isRebuilt": false,
      "address": "5317 WATSON AVE SW, BIRMINGHAM AL",
      "city": "BIRMINGHAM",
      "state": "AL",
      "beds": null,
      "baths": null,
      "sqft": null,
      "lotSize": null,
      "lat": 33.442366,
      "lng": -86.912724
    },
    {
      "propertyId": null,
      "attomId": 186495879,
      "offerDate": "2025-12-29",
      "offerPrice": 30000,
      "status": "recorder",
      "isRebuilt": false,
      "address": "7750 LAKE IN THE WOODS RD, TRUSSVILLE AL",
      "city": "TRUSSVILLE",
      "state": "AL",
      "beds": null,
      "baths": null,
      "sqft": null,
      "lotSize": null,
      "lat": 33.713676,
      "lng": -86.564121
    },
    {
      "propertyId": null,
      "attomId": 194047480,
      "offerDate": "2025-12-23",
      "offerPrice": 18000,
      "status": "recorder",
      "isRebuilt": false,
      "address": "2526 LEE AVE SW, BIRMINGHAM AL",
      "city": "BIRMINGHAM",
      "state": "AL",
      "beds": null,
      "baths": null,
      "sqft": null,
      "lotSize": null,
      "lat": 33.480732,
      "lng": -86.876866
    },
    {
      "propertyId": null,
      "attomId": 149919281,
      "offerDate": "2025-12-17",
      "offerPrice": 57500,
      "status": "recorder",
      "isRebuilt": false,
      "address": "921 25TH ST SW, BIRMINGHAM AL",
      "city": "BIRMINGHAM",
      "state": "AL",
      "beds": null,
      "baths": null,
      "sqft": null,
      "lotSize": null,
      "lat": 33.476756,
      "lng": -86.875031
    },
    {
      "propertyId": null,
      "attomId": 199911048,
      "offerDate": "2025-12-04",
      "offerPrice": 100000,
      "status": "recorder",
      "isRebuilt": false,
      "address": "1300 33RD ST N, BIRMINGHAM AL",
      "city": "BIRMINGHAM",
      "state": "AL",
      "beds": null,
      "baths": null,
      "sqft": null,
      "lotSize": null,
      "lat": 33.536987,
      "lng": -86.797695
    },
    {
      "propertyId": null,
      "attomId": 149312180,
      "offerDate": "2025-12-04",
      "offerPrice": 45500,
      "status": "recorder",
      "isRebuilt": false,
      "address": "5320 TERRACE Q, BIRMINGHAM AL",
      "city": "BIRMINGHAM",
      "state": "AL",
      "beds": null,
      "baths": null,
      "sqft": null,
      "lotSize": null,
      "lat": 33.480475,
      "lng": -86.885685
    },
    {
      "propertyId": null,
      "attomId": 26989045,
      "offerDate": "2025-11-21",
      "offerPrice": 92000,
      "status": "recorder",
      "isRebuilt": false,
      "address": "1412 12TH AVE N, BESSEMER AL",
      "city": "BESSEMER",
      "state": "AL",
      "beds": null,
      "baths": null,
      "sqft": null,
      "lotSize": null,
      "lat": 33.451345,
      "lng": -86.950502
    },
    {
      "propertyId": null,
      "attomId": 143688062,
      "offerDate": "2025-11-19",
      "offerPrice": 24000,
      "status": "recorder",
      "isRebuilt": false,
      "address": "1807 FAIRFAX AVE, BESSEMER AL",
      "city": "BESSEMER",
      "state": "AL",
      "beds": null,
      "baths": null,
      "sqft": null,
      "lotSize": null,
      "lat": 33.395578,
      "lng": -86.943131
    },
    {
      "propertyId": null,
      "attomId": 145734588,
      "offerDate": "2025-11-13",
      "offerPrice": 40000,
      "status": "recorder",
      "isRebuilt": false,
      "address": "1820 33RD STREET ENSLEY, BIRMINGHAM AL",
      "city": "BIRMINGHAM",
      "state": "AL",
      "beds": null,
      "baths": null,
      "sqft": null,
      "lotSize": null,
      "lat": 33.496476,
      "lng": -86.884219
    },
    {
      "propertyId": null,
      "attomId": 24799193,
      "offerDate": "2025-11-13",
      "offerPrice": 85000,
      "status": "recorder",
      "isRebuilt": false,
      "address": "416 HEARNE CIR, BIRMINGHAM AL",
      "city": "BIRMINGHAM",
      "state": "AL",
      "beds": null,
      "baths": null,
      "sqft": null,
      "lotSize": null,
      "lat": 33.596929,
      "lng": -86.714862
    },
    {
      "propertyId": null,
      "attomId": 192784021,
      "offerDate": "2025-11-06",
      "offerPrice": 72500,
      "status": "recorder",
      "isRebuilt": false,
      "address": "1106 12TH AVE, BIRMINGHAM AL",
      "city": "BIRMINGHAM",
      "state": "AL",
      "beds": null,
      "baths": null,
      "sqft": null,
      "lotSize": null,
      "lat": 33.450866,
      "lng": -86.946321
    },
    {
      "propertyId": null,
      "attomId": 153431565,
      "offerDate": "2025-11-04",
      "offerPrice": 72000,
      "status": "recorder",
      "isRebuilt": false,
      "address": "4941 43RD WAY N, BIRMINGHAM AL",
      "city": "BIRMINGHAM",
      "state": "AL",
      "beds": null,
      "baths": null,
      "sqft": null,
      "lotSize": null,
      "lat": 33.571829,
      "lng": -86.770406
    },
    {
      "propertyId": null,
      "attomId": 200440221,
      "offerDate": "2025-11-04",
      "offerPrice": 55000,
      "status": "recorder",
      "isRebuilt": false,
      "address": "5717 AVENUE O, BIRMINGHAM AL",
      "city": "BIRMINGHAM",
      "state": "AL",
      "beds": null,
      "baths": null,
      "sqft": null,
      "lotSize": null,
      "lat": 33.477973,
      "lng": -86.891538
    },
    {
      "propertyId": null,
      "attomId": 190417232,
      "offerDate": "2025-11-04",
      "offerPrice": 66500,
      "status": "recorder",
      "isRebuilt": false,
      "address": "1228 19TH PL SW, BIRMINGHAM AL",
      "city": "BIRMINGHAM",
      "state": "AL",
      "beds": null,
      "baths": null,
      "sqft": null,
      "lotSize": null,
      "lat": 33.475569,
      "lng": -86.869717
    },
    {
      "propertyId": null,
      "attomId": 203277203,
      "offerDate": "2025-10-31",
      "offerPrice": 30000,
      "status": "recorder",
      "isRebuilt": false,
      "address": "3009 PRINCE AVE, BIRMINGHAM AL",
      "city": "BIRMINGHAM",
      "state": "AL",
      "beds": null,
      "baths": null,
      "sqft": null,
      "lotSize": null,
      "lat": 33.497402,
      "lng": -86.881734
    },
    {
      "propertyId": null,
      "attomId": 9311999,
      "offerDate": "2025-10-30",
      "offerPrice": 78500,
      "status": "recorder",
      "isRebuilt": false,
      "address": "221 LAWSON RD, BIRMINGHAM AL",
      "city": "BIRMINGHAM",
      "state": "AL",
      "beds": null,
      "baths": null,
      "sqft": null,
      "lotSize": null,
      "lat": 33.598408,
      "lng": -86.713432
    },
    {
      "propertyId": null,
      "attomId": 54412706,
      "offerDate": "2025-10-21",
      "offerPrice": 30000,
      "status": "recorder",
      "isRebuilt": false,
      "address": "2712 24TH STREET ENSLEY, BIRMINGHAM AL",
      "city": "BIRMINGHAM",
      "state": "AL",
      "beds": null,
      "baths": null,
      "sqft": null,
      "lotSize": null,
      "lat": 33.505467,
      "lng": -86.871535
    },
    {
      "propertyId": null,
      "attomId": 40870075,
      "offerDate": "2025-10-20",
      "offerPrice": 56000,
      "status": "recorder",
      "isRebuilt": false,
      "address": "5722 TERRACE AVE, FAIRFIELD AL",
      "city": "FAIRFIELD",
      "state": "AL",
      "beds": null,
      "baths": null,
      "sqft": null,
      "lotSize": null,
      "lat": 33.480583,
      "lng": -86.91635
    },
    {
      "propertyId": null,
      "attomId": 145607492,
      "offerDate": "2025-10-17",
      "offerPrice": 92000,
      "status": "recorder",
      "isRebuilt": false,
      "address": "942 HILLCREST AVE, BIRMINGHAM AL",
      "city": "BIRMINGHAM",
      "state": "AL",
      "beds": null,
      "baths": null,
      "sqft": null,
      "lotSize": null,
      "lat": 33.592838,
      "lng": -86.6857
    },
    {
      "propertyId": null,
      "attomId": 7287722,
      "offerDate": "2025-10-09",
      "offerPrice": 59000,
      "status": "recorder",
      "isRebuilt": false,
      "address": "412 12TH ST SW, BIRMINGHAM AL",
      "city": "BIRMINGHAM",
      "state": "AL",
      "beds": null,
      "baths": null,
      "sqft": null,
      "lotSize": null,
      "lat": 33.496584,
      "lng": -86.854582
    },
    {
      "propertyId": null,
      "attomId": 13918038,
      "offerDate": "2025-10-03",
      "offerPrice": 71000,
      "status": "recorder",
      "isRebuilt": false,
      "address": "8025 1ST AVE S, BIRMINGHAM AL",
      "city": "BIRMINGHAM",
      "state": "AL",
      "beds": null,
      "baths": null,
      "sqft": null,
      "lotSize": null,
      "lat": 33.565584,
      "lng": -86.722659
    },
    {
      "propertyId": null,
      "attomId": 4172263,
      "offerDate": "2025-09-30",
      "offerPrice": 41500,
      "status": "recorder",
      "isRebuilt": false,
      "address": "8416 9TH AVE S, BIRMINGHAM AL",
      "city": "BIRMINGHAM",
      "state": "AL",
      "beds": null,
      "baths": null,
      "sqft": null,
      "lotSize": null,
      "lat": 33.567049,
      "lng": -86.707048
    },
    {
      "propertyId": null,
      "attomId": 7814694,
      "offerDate": "2025-09-11",
      "offerPrice": 68000,
      "status": "recorder",
      "isRebuilt": false,
      "address": "1420 47TH STREET ENSLEY, BIRMINGHAM AL",
      "city": "BIRMINGHAM",
      "state": "AL",
      "beds": null,
      "baths": null,
      "sqft": null,
      "lotSize": null,
      "lat": 33.486784,
      "lng": -86.893098
    },
    {
      "propertyId": null,
      "attomId": 140263967,
      "offerDate": "2025-09-05",
      "offerPrice": 70000,
      "status": "recorder",
      "isRebuilt": false,
      "address": "405 18TH AVE NW, CENTER POINT AL",
      "city": "CENTER POINT",
      "state": "AL",
      "beds": null,
      "baths": null,
      "sqft": null,
      "lotSize": null,
      "lat": 33.633519,
      "lng": -86.692141
    },
    {
      "propertyId": null,
      "attomId": 201825261,
      "offerDate": "2025-08-28",
      "offerPrice": 87000,
      "status": "recorder",
      "isRebuilt": false,
      "address": "6309 3RD AVE S, BIRMINGHAM AL",
      "city": "BIRMINGHAM",
      "state": "AL",
      "beds": null,
      "baths": null,
      "sqft": null,
      "lotSize": null,
      "lat": 33.543462,
      "lng": -86.741019
    },
    {
      "propertyId": null,
      "attomId": 198767483,
      "offerDate": "2025-08-27",
      "offerPrice": 20000,
      "status": "recorder",
      "isRebuilt": false,
      "address": "512 16TH ST SW, BIRMINGHAM AL",
      "city": "BIRMINGHAM",
      "state": "AL",
      "beds": null,
      "baths": null,
      "sqft": null,
      "lotSize": null,
      "lat": 33.490902,
      "lng": -86.860954
    },
    {
      "propertyId": null,
      "attomId": 203686999,
      "offerDate": "2025-08-25",
      "offerPrice": 80000,
      "status": "recorder",
      "isRebuilt": false,
      "address": "153 CAROL DR, BIRMINGHAM AL",
      "city": "BIRMINGHAM",
      "state": "AL",
      "beds": null,
      "baths": null,
      "sqft": null,
      "lotSize": null,
      "lat": 33.595942,
      "lng": -86.705552
    },
    {
      "propertyId": null,
      "attomId": 148385381,
      "offerDate": "2025-08-13",
      "offerPrice": 87500,
      "status": "recorder",
      "isRebuilt": false,
      "address": "1016 BELLE MEADE DR, BIRMINGHAM AL",
      "city": "BIRMINGHAM",
      "state": "AL",
      "beds": null,
      "baths": null,
      "sqft": null,
      "lotSize": null,
      "lat": 33.605311,
      "lng": -86.677238
    },
    {
      "propertyId": null,
      "attomId": 53198131,
      "offerDate": "2025-08-06",
      "offerPrice": 25000,
      "status": "recorder",
      "isRebuilt": false,
      "address": "7804 RUGBY AVE, BIRMINGHAM AL",
      "city": "BIRMINGHAM",
      "state": "AL",
      "beds": null,
      "baths": null,
      "sqft": null,
      "lotSize": null,
      "lat": 33.55886,
      "lng": -86.717101
    },
    {
      "propertyId": null,
      "attomId": 11009804,
      "offerDate": "2025-07-29",
      "offerPrice": 67500,
      "status": "recorder",
      "isRebuilt": false,
      "address": "2609 20TH STREET ENSLEY, BIRMINGHAM AL",
      "city": "BIRMINGHAM",
      "state": "AL",
      "beds": null,
      "baths": null,
      "sqft": null,
      "lotSize": null,
      "lat": 33.508227,
      "lng": -86.873806
    },
    {
      "propertyId": null,
      "attomId": 24482729,
      "offerDate": "2025-07-28",
      "offerPrice": 97500,
      "status": "recorder",
      "isRebuilt": false,
      "address": "932 FIVE MILE RD, BIRMINGHAM AL",
      "city": "BIRMINGHAM",
      "state": "AL",
      "beds": null,
      "baths": null,
      "sqft": null,
      "lotSize": null,
      "lat": 33.603917,
      "lng": -86.700615
    },
    {
      "propertyId": null,
      "attomId": 198715859,
      "offerDate": "2025-07-28",
      "offerPrice": 97000,
      "status": "recorder",
      "isRebuilt": false,
      "address": "741 9TH AVE W, BIRMINGHAM AL",
      "city": "BIRMINGHAM",
      "state": "AL",
      "beds": null,
      "baths": null,
      "sqft": null,
      "lotSize": null,
      "lat": 33.515788,
      "lng": -86.849452
    },
    {
      "propertyId": null,
      "attomId": 186411048,
      "offerDate": "2025-07-24",
      "offerPrice": 68000,
      "status": "recorder",
      "isRebuilt": false,
      "address": "9805 RED MILL RD, BIRMINGHAM AL",
      "city": "BIRMINGHAM",
      "state": "AL",
      "beds": null,
      "baths": null,
      "sqft": null,
      "lotSize": null,
      "lat": 33.596021,
      "lng": -86.71432
    },
    {
      "propertyId": null,
      "attomId": 197990418,
      "offerDate": "2025-07-22",
      "offerPrice": 65000,
      "status": "recorder",
      "isRebuilt": false,
      "address": "3111 AVENUE D, BIRMINGHAM AL",
      "city": "BIRMINGHAM",
      "state": "AL",
      "beds": null,
      "baths": null,
      "sqft": null,
      "lotSize": null,
      "lat": 33.503136,
      "lng": -86.905839
    },
    {
      "propertyId": null,
      "attomId": 27040927,
      "offerDate": "2025-07-22",
      "offerPrice": 64000,
      "status": "recorder",
      "isRebuilt": false,
      "address": "7840 8TH AVE S, BIRMINGHAM AL",
      "city": "BIRMINGHAM",
      "state": "AL",
      "beds": null,
      "baths": null,
      "sqft": null,
      "lotSize": null,
      "lat": 33.55875,
      "lng": -86.71401
    },
    {
      "propertyId": null,
      "attomId": 142708348,
      "offerDate": "2025-07-21",
      "offerPrice": 79000,
      "status": "recorder",
      "isRebuilt": false,
      "address": "2309 EUFAULA AVE, BIRMINGHAM AL",
      "city": "BIRMINGHAM",
      "state": "AL",
      "beds": null,
      "baths": null,
      "sqft": null,
      "lotSize": null,
      "lat": 33.505758,
      "lng": -86.867413
    },
    {
      "propertyId": null,
      "attomId": 192771468,
      "offerDate": "2025-07-21",
      "offerPrice": 85000,
      "status": "recorder",
      "isRebuilt": false,
      "address": "1657 LEE AVE SW, BIRMINGHAM AL",
      "city": "BIRMINGHAM",
      "state": "AL",
      "beds": null,
      "baths": null,
      "sqft": null,
      "lotSize": null,
      "lat": 33.488164,
      "lng": -86.862314
    },
    {
      "propertyId": null,
      "attomId": 192771339,
      "offerDate": "2025-07-18",
      "offerPrice": 70000,
      "status": "recorder",
      "isRebuilt": false,
      "address": "2016 26TH STREET ENSLEY, BIRMINGHAM AL",
      "city": "BIRMINGHAM",
      "state": "AL",
      "beds": null,
      "baths": null,
      "sqft": null,
      "lotSize": null,
      "lat": 33.503274,
      "lng": -86.880787
    },
    {
      "propertyId": null,
      "attomId": 12815707,
      "offerDate": "2025-07-18",
      "offerPrice": 98500,
      "status": "recorder",
      "isRebuilt": false,
      "address": "313 13TH TER NW, CENTER POINT AL",
      "city": "CENTER POINT",
      "state": "AL",
      "beds": null,
      "baths": null,
      "sqft": null,
      "lotSize": null,
      "lat": 33.620582,
      "lng": -86.692849
    },
    {
      "propertyId": null,
      "attomId": 54226013,
      "offerDate": "2025-07-18",
      "offerPrice": 49000,
      "status": "recorder",
      "isRebuilt": false,
      "address": "319 85TH ST N, BIRMINGHAM AL",
      "city": "BIRMINGHAM",
      "state": "AL",
      "beds": null,
      "baths": null,
      "sqft": null,
      "lotSize": null,
      "lat": 33.576111,
      "lng": -86.723878
    },
    {
      "propertyId": null,
      "attomId": 143118131,
      "offerDate": "2025-07-17",
      "offerPrice": 400000,
      "status": "recorder",
      "isRebuilt": false,
      "address": "2717 ENSLEY 5 POINTS W AVE, BIRMINGHAM AL",
      "city": "BIRMINGHAM",
      "state": "AL",
      "beds": null,
      "baths": null,
      "sqft": null,
      "lotSize": null,
      "lat": 33.502031,
      "lng": -86.883582
    },
    {
      "propertyId": null,
      "attomId": 43947308,
      "offerDate": "2025-07-16",
      "offerPrice": 85000,
      "status": "recorder",
      "isRebuilt": false,
      "address": "933 T ST, BIRMINGHAM AL",
      "city": "BIRMINGHAM",
      "state": "AL",
      "beds": null,
      "baths": null,
      "sqft": null,
      "lotSize": null,
      "lat": 33.592922,
      "lng": -86.680319
    },
    {
      "propertyId": null,
      "attomId": 146626931,
      "offerDate": "2025-07-15",
      "offerPrice": 65000,
      "status": "recorder",
      "isRebuilt": false,
      "address": "945 47TH STREET ENSLEY, BIRMINGHAM AL",
      "city": "BIRMINGHAM",
      "state": "AL",
      "beds": null,
      "baths": null,
      "sqft": null,
      "lotSize": null,
      "lat": 33.486911,
      "lng": -86.901354
    },
    {
      "propertyId": null,
      "attomId": 188268621,
      "offerDate": "2025-07-15",
      "offerPrice": 28000,
      "status": "recorder",
      "isRebuilt": false,
      "address": "108 E ANN DR SW, BIRMINGHAM AL",
      "city": "BIRMINGHAM",
      "state": "AL",
      "beds": null,
      "baths": null,
      "sqft": null,
      "lotSize": null,
      "lat": 33.466293,
      "lng": -86.864296
    },
    {
      "propertyId": null,
      "attomId": 40809718,
      "offerDate": "2025-07-14",
      "offerPrice": 33500,
      "status": "recorder",
      "isRebuilt": false,
      "address": "5121 MOLTON GRAY DR, BIRMINGHAM AL",
      "city": "BIRMINGHAM",
      "state": "AL",
      "beds": null,
      "baths": null,
      "sqft": null,
      "lotSize": null,
      "lat": 33.445793,
      "lng": -86.918727
    },
    {
      "propertyId": null,
      "attomId": 32776341,
      "offerDate": "2025-07-14",
      "offerPrice": 55000,
      "status": "recorder",
      "isRebuilt": false,
      "address": "2408 BROOKHAVEN AVE SW, BIRMINGHAM AL",
      "city": "BIRMINGHAM",
      "state": "AL",
      "beds": null,
      "baths": null,
      "sqft": null,
      "lotSize": null,
      "lat": 33.468157,
      "lng": -86.874743
    },
    {
      "propertyId": null,
      "attomId": 200407779,
      "offerDate": "2025-07-11",
      "offerPrice": 57000,
      "status": "recorder",
      "isRebuilt": false,
      "address": "2511 20TH PLACE ENSLEY, BIRMINGHAM AL",
      "city": "BIRMINGHAM",
      "state": "AL",
      "beds": null,
      "baths": null,
      "sqft": null,
      "lotSize": null,
      "lat": 33.508206,
      "lng": -86.876065
    },
    {
      "propertyId": null,
      "attomId": 51955455,
      "offerDate": "2025-07-11",
      "offerPrice": 82000,
      "status": "recorder",
      "isRebuilt": false,
      "address": "1526 42ND STREET ENSLEY, BIRMINGHAM AL",
      "city": "BIRMINGHAM",
      "state": "AL",
      "beds": null,
      "baths": null,
      "sqft": null,
      "lotSize": null,
      "lat": 33.491605,
      "lng": -86.890979
    },
    {
      "propertyId": null,
      "attomId": 984977,
      "offerDate": "2025-07-11",
      "offerPrice": 80000,
      "status": "recorder",
      "isRebuilt": false,
      "address": "4804 TERRACE M, BIRMINGHAM AL",
      "city": "BIRMINGHAM",
      "state": "AL",
      "beds": null,
      "baths": null,
      "sqft": null,
      "lotSize": null,
      "lat": 33.485222,
      "lng": -86.894915
    },
    {
      "propertyId": null,
      "attomId": 291714,
      "offerDate": "2025-07-11",
      "offerPrice": 30000,
      "status": "recorder",
      "isRebuilt": false,
      "address": "1805 SAINT CHARLES AVE SW, BIRMINGHAM AL",
      "city": "BIRMINGHAM",
      "state": "AL",
      "beds": null,
      "baths": null,
      "sqft": null,
      "lotSize": null,
      "lat": 33.488118,
      "lng": -86.866085
    },
    {
      "propertyId": null,
      "attomId": 8940795,
      "offerDate": "2025-07-10",
      "offerPrice": 60000,
      "status": "recorder",
      "isRebuilt": false,
      "address": "308 10TH ST S, BESSEMER AL",
      "city": "BESSEMER",
      "state": "AL",
      "beds": null,
      "baths": null,
      "sqft": null,
      "lotSize": null,
      "lat": 33.389572,
      "lng": -86.955363
    },
    {
      "propertyId": null,
      "attomId": 43947764,
      "offerDate": "2025-07-09",
      "offerPrice": 75000,
      "status": "recorder",
      "isRebuilt": false,
      "address": "937 FIVE MILE RD, BIRMINGHAM AL",
      "city": "BIRMINGHAM",
      "state": "AL",
      "beds": null,
      "baths": null,
      "sqft": null,
      "lotSize": null,
      "lat": 33.604157,
      "lng": -86.699909
    },
    {
      "propertyId": null,
      "attomId": 155376206,
      "offerDate": "2025-07-09",
      "offerPrice": 35000,
      "status": "recorder",
      "isRebuilt": false,
      "address": "829 51ST STREET ENSLEY, BIRMINGHAM AL",
      "city": "BIRMINGHAM",
      "state": "AL",
      "beds": null,
      "baths": null,
      "sqft": null,
      "lotSize": null,
      "lat": 33.482812,
      "lng": -86.903518
    },
    {
      "propertyId": null,
      "attomId": 9409118,
      "offerDate": "2025-07-08",
      "offerPrice": 75500,
      "status": "recorder",
      "isRebuilt": false,
      "address": "963 3RD ST W, BIRMINGHAM AL",
      "city": "BIRMINGHAM",
      "state": "AL",
      "beds": null,
      "baths": null,
      "sqft": null,
      "lotSize": null,
      "lat": 33.517869,
      "lng": -86.840433
    },
    {
      "propertyId": null,
      "attomId": 8745244,
      "offerDate": "2025-07-08",
      "offerPrice": 81000,
      "status": "recorder",
      "isRebuilt": false,
      "address": "412 TUPELO WAY, CENTER POINT AL",
      "city": "CENTER POINT",
      "state": "AL",
      "beds": null,
      "baths": null,
      "sqft": null,
      "lotSize": null,
      "lat": 33.639203,
      "lng": -86.693034
    },
    {
      "propertyId": null,
      "attomId": 204078179,
      "offerDate": "2025-06-23",
      "offerPrice": 28000,
      "status": "recorder",
      "isRebuilt": false,
      "address": "2005 SNAVELY AVE SW, BIRMINGHAM AL",
      "city": "BIRMINGHAM",
      "state": "AL",
      "beds": null,
      "baths": null,
      "sqft": null,
      "lotSize": null,
      "lat": 33.46635437011719,
      "lng": -86.870139
    },
    {
      "propertyId": null,
      "attomId": 203129141,
      "offerDate": "2025-06-23",
      "offerPrice": 57000,
      "status": "recorder",
      "isRebuilt": false,
      "address": "617 7TH ST W, BIRMINGHAM AL",
      "city": "BIRMINGHAM",
      "state": "AL",
      "beds": null,
      "baths": null,
      "sqft": null,
      "lotSize": null,
      "lat": 33.511,
      "lng": -86.847129
    },
    {
      "propertyId": null,
      "attomId": 53552968,
      "offerDate": "2025-06-10",
      "offerPrice": 50000,
      "status": "recorder",
      "isRebuilt": false,
      "address": "6724 2ND AVE S, BIRMINGHAM AL",
      "city": "BIRMINGHAM",
      "state": "AL",
      "beds": null,
      "baths": null,
      "sqft": null,
      "lotSize": null,
      "lat": 33.54912,
      "lng": -86.736052
    },
    {
      "propertyId": null,
      "attomId": 20820663,
      "offerDate": "2025-06-04",
      "offerPrice": 46000,
      "status": "recorder",
      "isRebuilt": false,
      "address": "1757 48TH STREET ENSLEY, BIRMINGHAM AL",
      "city": "BIRMINGHAM",
      "state": "AL",
      "beds": null,
      "baths": null,
      "sqft": null,
      "lotSize": null,
      "lat": 33.485539,
      "lng": -86.884862
    },
    {
      "propertyId": null,
      "attomId": 34863861,
      "offerDate": "2025-05-29",
      "offerPrice": 85000,
      "status": "recorder",
      "isRebuilt": false,
      "address": "2537 3RD ST NE, CENTER POINT AL",
      "city": "CENTER POINT",
      "state": "AL",
      "beds": null,
      "baths": null,
      "sqft": null,
      "lotSize": null,
      "lat": 33.653575,
      "lng": -86.677118
    },
    {
      "propertyId": null,
      "attomId": 52009734,
      "offerDate": "2025-05-29",
      "offerPrice": 87000,
      "status": "recorder",
      "isRebuilt": false,
      "address": "1133 WOODSLEE ST, BIRMINGHAM AL",
      "city": "BIRMINGHAM",
      "state": "AL",
      "beds": null,
      "baths": null,
      "sqft": null,
      "lotSize": null,
      "lat": 33.616301,
      "lng": -86.691983
    },
    {
      "propertyId": null,
      "attomId": 52011654,
      "offerDate": "2025-05-27",
      "offerPrice": 32000,
      "status": "recorder",
      "isRebuilt": false,
      "address": "2124 47TH PLACE ENSLEY, BIRMINGHAM AL",
      "city": "BIRMINGHAM",
      "state": "AL",
      "beds": null,
      "baths": null,
      "sqft": null,
      "lotSize": null,
      "lat": 33.492242,
      "lng": -86.877986
    },
    {
      "propertyId": null,
      "attomId": 8745245,
      "offerDate": "2025-05-21",
      "offerPrice": 90900,
      "status": "recorder",
      "isRebuilt": false,
      "address": "576 SUN VALLEY RD, CENTER POINT AL",
      "city": "CENTER POINT",
      "state": "AL",
      "beds": null,
      "baths": null,
      "sqft": null,
      "lotSize": null,
      "lat": 33.639415,
      "lng": -86.701431
    },
    {
      "propertyId": null,
      "attomId": 10513530,
      "offerDate": "2025-05-13",
      "offerPrice": 25000,
      "status": "recorder",
      "isRebuilt": false,
      "address": "1893 PRINCETON CT SW, BIRMINGHAM AL",
      "city": "BIRMINGHAM",
      "state": "AL",
      "beds": null,
      "baths": null,
      "sqft": null,
      "lotSize": null,
      "lat": 33.487358,
      "lng": -86.869907
    },
    {
      "propertyId": null,
      "attomId": 201495602,
      "offerDate": "2025-05-13",
      "offerPrice": 47000,
      "status": "recorder",
      "isRebuilt": false,
      "address": "1441 CREEL ST, BIRMINGHAM AL",
      "city": "BIRMINGHAM",
      "state": "AL",
      "beds": null,
      "baths": null,
      "sqft": null,
      "lotSize": null,
      "lat": 33.461161,
      "lng": -86.903983
    },
    {
      "propertyId": null,
      "attomId": 9397921,
      "offerDate": "2025-05-12",
      "offerPrice": 70000,
      "status": "recorder",
      "isRebuilt": false,
      "address": "7229 3RD AVE S, BIRMINGHAM AL",
      "city": "BIRMINGHAM",
      "state": "AL",
      "beds": null,
      "baths": null,
      "sqft": null,
      "lotSize": null,
      "lat": 33.553767,
      "lng": -86.728856
    },
    {
      "propertyId": null,
      "attomId": 43954024,
      "offerDate": "2025-05-12",
      "offerPrice": 35000,
      "status": "recorder",
      "isRebuilt": false,
      "address": "2105 46TH PLACE ENSLEY, BIRMINGHAM AL",
      "city": "BIRMINGHAM",
      "state": "AL",
      "beds": null,
      "baths": null,
      "sqft": null,
      "lotSize": null,
      "lat": 33.492909,
      "lng": -86.879841
    },
    {
      "propertyId": null,
      "attomId": 190083409,
      "offerDate": "2025-05-12",
      "offerPrice": 20000,
      "status": "recorder",
      "isRebuilt": false,
      "address": "2619 AVENUE F, BIRMINGHAM AL",
      "city": "BIRMINGHAM",
      "state": "AL",
      "beds": null,
      "baths": null,
      "sqft": null,
      "lotSize": null,
      "lat": 33.505887,
      "lng": -86.900622
    },
    {
      "propertyId": null,
      "attomId": 147157300,
      "offerDate": "2025-05-07",
      "offerPrice": 80000,
      "status": "recorder",
      "isRebuilt": false,
      "address": "1300 33RD STREET ENSLEY, BIRMINGHAM AL",
      "city": "BIRMINGHAM",
      "state": "AL",
      "beds": null,
      "baths": null,
      "sqft": null,
      "lotSize": null,
      "lat": 33.496779,
      "lng": -86.895195
    },
    {
      "propertyId": null,
      "attomId": 191889774,
      "offerDate": "2025-05-07",
      "offerPrice": 72000,
      "status": "recorder",
      "isRebuilt": false,
      "address": "514 81ST ST S, BIRMINGHAM AL",
      "city": "BIRMINGHAM",
      "state": "AL",
      "beds": null,
      "baths": null,
      "sqft": null,
      "lotSize": null,
      "lat": 33.563821,
      "lng": -86.717005
    },
    {
      "propertyId": null,
      "attomId": 11014425,
      "offerDate": "2025-05-06",
      "offerPrice": 50000,
      "status": "recorder",
      "isRebuilt": false,
      "address": "7208 OPORTO AVE, BIRMINGHAM AL",
      "city": "BIRMINGHAM",
      "state": "AL",
      "beds": null,
      "baths": null,
      "sqft": null,
      "lotSize": null,
      "lat": 33.550032,
      "lng": -86.71874
    },
    {
      "propertyId": null,
      "attomId": 202733375,
      "offerDate": "2025-04-30",
      "offerPrice": 62000,
      "status": "recorder",
      "isRebuilt": false,
      "address": "927 MASON AVE SW, BIRMINGHAM AL",
      "city": "BIRMINGHAM",
      "state": "AL",
      "beds": null,
      "baths": null,
      "sqft": null,
      "lotSize": null,
      "lat": 33.476738,
      "lng": -86.843182
    },
    {
      "propertyId": null,
      "attomId": 197203898,
      "offerDate": "2025-04-30",
      "offerPrice": 72500,
      "status": "recorder",
      "isRebuilt": false,
      "address": "1420 44TH STREET ENSLEY, BIRMINGHAM AL",
      "city": "BIRMINGHAM",
      "state": "AL",
      "beds": null,
      "baths": null,
      "sqft": null,
      "lotSize": null,
      "lat": 33.489677,
      "lng": -86.892915
    },
    {
      "propertyId": null,
      "attomId": 11390146,
      "offerDate": "2025-04-28",
      "offerPrice": 80000,
      "status": "recorder",
      "isRebuilt": false,
      "address": "1124 EADOM PL, BIRMINGHAM AL",
      "city": "BIRMINGHAM",
      "state": "AL",
      "beds": null,
      "baths": null,
      "sqft": null,
      "lotSize": null,
      "lat": 33.588679,
      "lng": -86.677876
    },
    {
      "propertyId": null,
      "attomId": 1668649,
      "offerDate": "2025-04-28",
      "offerPrice": 39000,
      "status": "recorder",
      "isRebuilt": false,
      "address": "518 41ST ST, FAIRFIELD AL",
      "city": "FAIRFIELD",
      "state": "AL",
      "beds": null,
      "baths": null,
      "sqft": null,
      "lotSize": null,
      "lat": 33.494383,
      "lng": -86.910356
    },
    {
      "propertyId": null,
      "attomId": 200848073,
      "offerDate": "2025-04-25",
      "offerPrice": 40000,
      "status": "recorder",
      "isRebuilt": false,
      "address": "1029 ETOWAH ST, BIRMINGHAM AL",
      "city": "BIRMINGHAM",
      "state": "AL",
      "beds": null,
      "baths": null,
      "sqft": null,
      "lotSize": null,
      "lat": 33.573235,
      "lng": -86.767391
    },
    {
      "propertyId": null,
      "attomId": 143059798,
      "offerDate": "2025-04-25",
      "offerPrice": 62500,
      "status": "recorder",
      "isRebuilt": false,
      "address": "3113 AVENUE S, BIRMINGHAM AL",
      "city": "BIRMINGHAM",
      "state": "AL",
      "beds": null,
      "baths": null,
      "sqft": null,
      "lotSize": null,
      "lat": 33.497467,
      "lng": -86.882909
    },
    {
      "propertyId": null,
      "attomId": 183585523,
      "offerDate": "2025-04-23",
      "offerPrice": 30000,
      "status": "recorder",
      "isRebuilt": false,
      "address": "2128 EARLY ST, MONTGOMERY AL",
      "city": "MONTGOMERY",
      "state": "AL",
      "beds": null,
      "baths": null,
      "sqft": null,
      "lotSize": null,
      "lat": 32.358958,
      "lng": -86.328051
    },
    {
      "propertyId": null,
      "attomId": 9312691,
      "offerDate": "2025-04-23",
      "offerPrice": 47000,
      "status": "recorder",
      "isRebuilt": false,
      "address": "516 14TH ST SW, BIRMINGHAM AL",
      "city": "BIRMINGHAM",
      "state": "AL",
      "beds": null,
      "baths": null,
      "sqft": null,
      "lotSize": null,
      "lat": 33.493375,
      "lng": -86.856769
    },
    {
      "propertyId": null,
      "attomId": 199390748,
      "offerDate": "2025-04-15",
      "offerPrice": 11000,
      "status": "recorder",
      "isRebuilt": false,
      "address": "2113 RAMBOW AVE SW, BIRMINGHAM AL",
      "city": "BIRMINGHAM",
      "state": "AL",
      "beds": null,
      "baths": null,
      "sqft": null,
      "lotSize": null,
      "lat": 33.455683,
      "lng": -86.871216
    },
    {
      "propertyId": null,
      "attomId": 193994588,
      "offerDate": "2025-04-03",
      "offerPrice": 47000,
      "status": "recorder",
      "isRebuilt": false,
      "address": "924 26TH ST SW, BIRMINGHAM AL",
      "city": "BIRMINGHAM",
      "state": "AL",
      "beds": null,
      "baths": null,
      "sqft": null,
      "lotSize": null,
      "lat": 33.475434,
      "lng": -86.876824
    },
    {
      "propertyId": null,
      "attomId": 40849386,
      "offerDate": "2025-04-02",
      "offerPrice": 52000,
      "status": "recorder",
      "isRebuilt": false,
      "address": "1209 8TH ST, MIDFIELD AL",
      "city": "MIDFIELD",
      "state": "AL",
      "beds": null,
      "baths": null,
      "sqft": null,
      "lotSize": null,
      "lat": 33.450315,
      "lng": -86.942678
    },
    {
      "propertyId": null,
      "attomId": 148920824,
      "offerDate": "2025-04-02",
      "offerPrice": 42000,
      "status": "recorder",
      "isRebuilt": false,
      "address": "624 83RD PL S, BIRMINGHAM AL",
      "city": "BIRMINGHAM",
      "state": "AL",
      "beds": null,
      "baths": null,
      "sqft": null,
      "lotSize": null,
      "lat": 33.567467,
      "lng": -86.712762
    },
    {
      "propertyId": null,
      "attomId": 187324282,
      "offerDate": "2025-03-28",
      "offerPrice": 48000,
      "status": "recorder",
      "isRebuilt": false,
      "address": "1149 15TH ST SW, BIRMINGHAM AL",
      "city": "BIRMINGHAM",
      "state": "AL",
      "beds": null,
      "baths": null,
      "sqft": null,
      "lotSize": null,
      "lat": 33.485528,
      "lng": -86.851994
    },
    {
      "propertyId": null,
      "attomId": 194046891,
      "offerDate": "2025-03-18",
      "offerPrice": 101000,
      "status": "recorder",
      "isRebuilt": false,
      "address": "4212 50TH AVE N, BIRMINGHAM AL",
      "city": "BIRMINGHAM",
      "state": "AL",
      "beds": null,
      "baths": null,
      "sqft": null,
      "lotSize": null,
      "lat": 33.572658,
      "lng": -86.774408
    },
    {
      "propertyId": null,
      "attomId": 203517775,
      "offerDate": "2025-03-18",
      "offerPrice": 50000,
      "status": "recorder",
      "isRebuilt": false,
      "address": "3120 32ND AVE N, BIRMINGHAM AL",
      "city": "BIRMINGHAM",
      "state": "AL",
      "beds": null,
      "baths": null,
      "sqft": null,
      "lotSize": null,
      "lat": 33.552621,
      "lng": -86.821783
    },
    {
      "propertyId": null,
      "attomId": 54471830,
      "offerDate": "2025-03-18",
      "offerPrice": 26000,
      "status": "recorder",
      "isRebuilt": false,
      "address": "1520 34TH AVE N, BIRMINGHAM AL",
      "city": "BIRMINGHAM",
      "state": "AL",
      "beds": null,
      "baths": null,
      "sqft": null,
      "lotSize": null,
      "lat": 33.551606,
      "lng": -86.834661
    },
    {
      "propertyId": null,
      "attomId": 4073926,
      "offerDate": "2025-03-18",
      "offerPrice": 55000,
      "status": "recorder",
      "isRebuilt": false,
      "address": "1329 WOODWARD RD, BIRMINGHAM AL",
      "city": "BIRMINGHAM",
      "state": "AL",
      "beds": null,
      "baths": null,
      "sqft": null,
      "lotSize": null,
      "lat": 33.464987,
      "lng": -86.904076
    },
    {
      "propertyId": null,
      "attomId": 153426405,
      "offerDate": "2025-03-18",
      "offerPrice": 48500,
      "status": "recorder",
      "isRebuilt": false,
      "address": "1252 DOGWOOD RD, ADAMSVILLE AL",
      "city": "ADAMSVILLE",
      "state": "AL",
      "beds": null,
      "baths": null,
      "sqft": null,
      "lotSize": null,
      "lat": 33.587523,
      "lng": -86.986765
    },
    {
      "propertyId": null,
      "attomId": 204019383,
      "offerDate": "2025-03-14",
      "offerPrice": 100000,
      "status": "recorder",
      "isRebuilt": false,
      "address": "2335 20TH PLACE ENSLEY, BIRMINGHAM AL",
      "city": "BIRMINGHAM",
      "state": "AL",
      "beds": null,
      "baths": null,
      "sqft": null,
      "lotSize": null,
      "lat": 33.508248,
      "lng": -86.876937
    },
    {
      "propertyId": null,
      "attomId": 153098500,
      "offerDate": "2025-03-14",
      "offerPrice": 40000,
      "status": "recorder",
      "isRebuilt": false,
      "address": "4717 COURT S, BIRMINGHAM AL",
      "city": "BIRMINGHAM",
      "state": "AL",
      "beds": null,
      "baths": null,
      "sqft": null,
      "lotSize": null,
      "lat": 33.48996,
      "lng": -86.881176
    },
    {
      "propertyId": null,
      "attomId": 53938991,
      "offerDate": "2025-03-14",
      "offerPrice": 40000,
      "status": "recorder",
      "isRebuilt": false,
      "address": "4721 TERRACE M, BIRMINGHAM AL",
      "city": "BIRMINGHAM",
      "state": "AL",
      "beds": null,
      "baths": null,
      "sqft": null,
      "lotSize": null,
      "lat": 33.485759,
      "lng": -86.894305
    },
    {
      "propertyId": null,
      "attomId": 194059534,
      "offerDate": "2025-03-14",
      "offerPrice": 42000,
      "status": "recorder",
      "isRebuilt": false,
      "address": "728 39TH PL, FAIRFIELD AL",
      "city": "FAIRFIELD",
      "state": "AL",
      "beds": null,
      "baths": null,
      "sqft": null,
      "lotSize": null,
      "lat": 33.495101,
      "lng": -86.906033
    },
    {
      "propertyId": null,
      "attomId": 193899820,
      "offerDate": "2025-03-07",
      "offerPrice": 28000,
      "status": "recorder",
      "isRebuilt": false,
      "address": "7213 NAPLES AVE, BIRMINGHAM AL",
      "city": "BIRMINGHAM",
      "state": "AL",
      "beds": null,
      "baths": null,
      "sqft": null,
      "lotSize": null,
      "lat": 33.550039,
      "lng": -86.719265
    },
    {
      "propertyId": null,
      "attomId": 146622558,
      "offerDate": "2025-03-04",
      "offerPrice": 105000,
      "status": "recorder",
      "isRebuilt": false,
      "address": "133 REDSTONE DR, BIRMINGHAM AL",
      "city": "BIRMINGHAM",
      "state": "AL",
      "beds": null,
      "baths": null,
      "sqft": null,
      "lotSize": null,
      "lat": 33.612067,
      "lng": -86.716486
    },
    {
      "propertyId": null,
      "attomId": 204077588,
      "offerDate": "2025-02-21",
      "offerPrice": 105000,
      "status": "recorder",
      "isRebuilt": false,
      "address": "1025 47TH STREET ENSLEY, BIRMINGHAM AL",
      "city": "BIRMINGHAM",
      "state": "AL",
      "beds": null,
      "baths": null,
      "sqft": null,
      "lotSize": null,
      "lat": 33.486876,
      "lng": -86.899258
    },
    {
      "propertyId": null,
      "attomId": 201835058,
      "offerDate": "2025-02-21",
      "offerPrice": 87000,
      "status": "recorder",
      "isRebuilt": false,
      "address": "2745 21ST STREET ENSLEY, BIRMINGHAM AL",
      "city": "BIRMINGHAM",
      "state": "AL",
      "beds": null,
      "baths": null,
      "sqft": null,
      "lotSize": null,
      "lat": 33.506975,
      "lng": -86.870222
    },
    {
      "propertyId": null,
      "attomId": 27658921,
      "offerDate": "2025-02-21",
      "offerPrice": 28000,
      "status": "recorder",
      "isRebuilt": false,
      "address": "1322 FRISCO ST, BIRMINGHAM AL",
      "city": "BIRMINGHAM",
      "state": "AL",
      "beds": null,
      "baths": null,
      "sqft": null,
      "lotSize": null,
      "lat": 33.498499,
      "lng": -86.919243
    },
    {
      "propertyId": null,
      "attomId": 941584,
      "offerDate": "2025-02-19",
      "offerPrice": 72000,
      "status": "recorder",
      "isRebuilt": false,
      "address": "609 34TH ST S, BIRMINGHAM AL",
      "city": "BIRMINGHAM",
      "state": "AL",
      "beds": null,
      "baths": null,
      "sqft": null,
      "lotSize": null,
      "lat": 33.516038,
      "lng": -86.780987
    },
    {
      "propertyId": null,
      "attomId": 8597779,
      "offerDate": "2025-02-04",
      "offerPrice": 357000,
      "status": "recorder",
      "isRebuilt": false,
      "address": "552 OSCEOLA CIR, FAIRFIELD AL",
      "city": "FAIRFIELD",
      "state": "AL",
      "beds": null,
      "baths": null,
      "sqft": null,
      "lotSize": null,
      "lat": 33.474706,
      "lng": -86.925453
    },
    {
      "propertyId": null,
      "attomId": 26656952,
      "offerDate": "2025-02-04",
      "offerPrice": 115000,
      "status": "recorder",
      "isRebuilt": false,
      "address": "1625 3RD PL NW, CENTER POINT AL",
      "city": "CENTER POINT",
      "state": "AL",
      "beds": null,
      "baths": null,
      "sqft": null,
      "lotSize": null,
      "lat": 33.629731,
      "lng": -86.691933
    },
    {
      "propertyId": null,
      "attomId": 143333509,
      "offerDate": "2025-01-24",
      "offerPrice": 46500,
      "status": "recorder",
      "isRebuilt": false,
      "address": "9601 SHORT ST, BIRMINGHAM AL",
      "city": "BIRMINGHAM",
      "state": "AL",
      "beds": null,
      "baths": null,
      "sqft": null,
      "lotSize": null,
      "lat": 33.594516,
      "lng": -86.747601
    },
    {
      "propertyId": null,
      "attomId": 9578331,
      "offerDate": "2025-01-24",
      "offerPrice": 65000,
      "status": "recorder",
      "isRebuilt": false,
      "address": "6715 COURT N, BIRMINGHAM AL",
      "city": "BIRMINGHAM",
      "state": "AL",
      "beds": null,
      "baths": null,
      "sqft": null,
      "lotSize": null,
      "lat": 33.468593,
      "lng": -86.894258
    },
    {
      "propertyId": null,
      "attomId": 146367084,
      "offerDate": "2025-01-24",
      "offerPrice": 48500,
      "status": "recorder",
      "isRebuilt": false,
      "address": "7912 1ST AVE S, BIRMINGHAM AL",
      "city": "BIRMINGHAM",
      "state": "AL",
      "beds": null,
      "baths": null,
      "sqft": null,
      "lotSize": null,
      "lat": 33.564244,
      "lng": -86.72436
    },
    {
      "propertyId": null,
      "attomId": 190417269,
      "offerDate": "2025-01-14",
      "offerPrice": 77500,
      "status": "recorder",
      "isRebuilt": false,
      "address": "2816 SNAVELY AVE SW, BIRMINGHAM AL",
      "city": "BIRMINGHAM",
      "state": "AL",
      "beds": null,
      "baths": null,
      "sqft": null,
      "lotSize": null,
      "lat": 33.467289,
      "lng": -86.879676
    },
    {
      "propertyId": null,
      "attomId": 16135361,
      "offerDate": "2025-01-08",
      "offerPrice": 75000,
      "status": "recorder",
      "isRebuilt": false,
      "address": "7904 1ST AVE S, BIRMINGHAM AL",
      "city": "BIRMINGHAM",
      "state": "AL",
      "beds": null,
      "baths": null,
      "sqft": null,
      "lotSize": null,
      "lat": 33.564075,
      "lng": -86.724469
    },
    {
      "propertyId": null,
      "attomId": 54621238,
      "offerDate": "2025-01-08",
      "offerPrice": 45000,
      "status": "recorder",
      "isRebuilt": false,
      "address": "3017 PIKE RD, BIRMINGHAM AL",
      "city": "BIRMINGHAM",
      "state": "AL",
      "beds": null,
      "baths": null,
      "sqft": null,
      "lotSize": null,
      "lat": 33.512767,
      "lng": -86.867278
    },
    {
      "propertyId": null,
      "attomId": 194975076,
      "offerDate": "2025-01-08",
      "offerPrice": 685714,
      "status": "recorder",
      "isRebuilt": false,
      "address": "1360 5TH PL NW, CENTER POINT AL",
      "city": "CENTER POINT",
      "state": "AL",
      "beds": null,
      "baths": null,
      "sqft": null,
      "lotSize": null,
      "lat": 33.622899,
      "lng": -86.698018
    },
    {
      "propertyId": null,
      "attomId": 204019260,
      "offerDate": "2025-01-08",
      "offerPrice": 95000,
      "status": "recorder",
      "isRebuilt": false,
      "address": "425 5TH ST, FORESTDALE AL",
      "city": "FORESTDALE",
      "state": "AL",
      "beds": null,
      "baths": null,
      "sqft": null,
      "lotSize": null,
      "lat": 33.52980041503906,
      "lng": -86.886825
    },
    {
      "propertyId": null,
      "attomId": 197194763,
      "offerDate": "2025-01-08",
      "offerPrice": 28000,
      "status": "recorder",
      "isRebuilt": false,
      "address": "1213 AVENUE H, BIRMINGHAM AL",
      "city": "BIRMINGHAM",
      "state": "AL",
      "beds": null,
      "baths": null,
      "sqft": null,
      "lotSize": null,
      "lat": 33.517134,
      "lng": -86.888878
    },
    {
      "propertyId": null,
      "attomId": 143659403,
      "offerDate": "2025-01-08",
      "offerPrice": 114286,
      "status": "recorder",
      "isRebuilt": false,
      "address": "1317 5TH PL NW, CENTER POINT AL",
      "city": "CENTER POINT",
      "state": "AL",
      "beds": null,
      "baths": null,
      "sqft": null,
      "lotSize": null,
      "lat": 33.620962,
      "lng": -86.697399
    },
    {
      "propertyId": null,
      "attomId": 142103930,
      "offerDate": "2024-12-27",
      "offerPrice": 60000,
      "status": "recorder",
      "isRebuilt": false,
      "address": "1443 LAKE LN NE, BIRMINGHAM AL",
      "city": "BIRMINGHAM",
      "state": "AL",
      "beds": null,
      "baths": null,
      "sqft": null,
      "lotSize": null,
      "lat": 33.625319,
      "lng": -86.679862
    },
    {
      "propertyId": null,
      "attomId": 203353796,
      "offerDate": "2024-12-26",
      "offerPrice": 60000,
      "status": "recorder",
      "isRebuilt": false,
      "address": "8413 3RD AVE N, BIRMINGHAM AL",
      "city": "BIRMINGHAM",
      "state": "AL",
      "beds": null,
      "baths": null,
      "sqft": null,
      "lotSize": null,
      "lat": 33.57432,
      "lng": -86.723758
    },
    {
      "propertyId": null,
      "attomId": 52333809,
      "offerDate": "2024-12-26",
      "offerPrice": 85000,
      "status": "recorder",
      "isRebuilt": false,
      "address": "2201 BEULAH AVE SW, BIRMINGHAM AL",
      "city": "BIRMINGHAM",
      "state": "AL",
      "beds": null,
      "baths": null,
      "sqft": null,
      "lotSize": null,
      "lat": 33.477372,
      "lng": -86.871175
    },
    {
      "propertyId": null,
      "attomId": 24762283,
      "offerDate": "2024-12-26",
      "offerPrice": 83000,
      "status": "recorder",
      "isRebuilt": false,
      "address": "2409 3RD PL NW, CENTER POINT AL",
      "city": "CENTER POINT",
      "state": "AL",
      "beds": null,
      "baths": null,
      "sqft": null,
      "lotSize": null,
      "lat": 33.650086,
      "lng": -86.692493
    },
    {
      "propertyId": null,
      "attomId": 53198333,
      "offerDate": "2024-12-26",
      "offerPrice": 93000,
      "status": "recorder",
      "isRebuilt": false,
      "address": "1333 5TH PL NW, CENTER POINT AL",
      "city": "CENTER POINT",
      "state": "AL",
      "beds": null,
      "baths": null,
      "sqft": null,
      "lotSize": null,
      "lat": 33.62173,
      "lng": -86.6974
    },
    {
      "propertyId": null,
      "attomId": 158334732,
      "offerDate": "2024-12-04",
      "offerPrice": 114101,
      "status": "recorder",
      "isRebuilt": false,
      "address": "829 HILLVIEW DR, BIRMINGHAM AL",
      "city": "BIRMINGHAM",
      "state": "AL",
      "beds": null,
      "baths": null,
      "sqft": null,
      "lotSize": null,
      "lat": 33.603678,
      "lng": -86.675158
    },
    {
      "propertyId": null,
      "attomId": 1996786,
      "offerDate": "2024-12-04",
      "offerPrice": 110500,
      "status": "recorder",
      "isRebuilt": false,
      "address": "620 ANNIE LAURA DR, BIRMINGHAM AL",
      "city": "BIRMINGHAM",
      "state": "AL",
      "beds": null,
      "baths": null,
      "sqft": null,
      "lotSize": null,
      "lat": 33.597751,
      "lng": -86.70224
    },
    {
      "propertyId": null,
      "attomId": 45969006,
      "offerDate": "2024-12-04",
      "offerPrice": 110000,
      "status": "recorder",
      "isRebuilt": false,
      "address": "621 CAROLYN CT, BIRMINGHAM AL",
      "city": "BIRMINGHAM",
      "state": "AL",
      "beds": null,
      "baths": null,
      "sqft": null,
      "lotSize": null,
      "lat": 33.585668,
      "lng": -86.691134
    },
    {
      "propertyId": null,
      "attomId": 152690951,
      "offerDate": "2024-12-04",
      "offerPrice": 95000,
      "status": "recorder",
      "isRebuilt": false,
      "address": "8215 RUGBY AVE, BIRMINGHAM AL",
      "city": "BIRMINGHAM",
      "state": "AL",
      "beds": null,
      "baths": null,
      "sqft": null,
      "lotSize": null,
      "lat": 33.566863,
      "lng": -86.714426
    },
    {
      "propertyId": null,
      "attomId": 143807189,
      "offerDate": "2024-12-04",
      "offerPrice": 85000,
      "status": "recorder",
      "isRebuilt": false,
      "address": "9036 BEVERLY DR N, BIRMINGHAM AL",
      "city": "BIRMINGHAM",
      "state": "AL",
      "beds": null,
      "baths": null,
      "sqft": null,
      "lotSize": null,
      "lat": 33.58495,
      "lng": -86.719544
    },
    {
      "propertyId": null,
      "attomId": 143807378,
      "offerDate": "2024-12-04",
      "offerPrice": 100000,
      "status": "recorder",
      "isRebuilt": false,
      "address": "7929 6TH AVE N, BIRMINGHAM AL",
      "city": "BIRMINGHAM",
      "state": "AL",
      "beds": null,
      "baths": null,
      "sqft": null,
      "lotSize": null,
      "lat": 33.568664,
      "lng": -86.732674
    },
    {
      "propertyId": null,
      "attomId": 195617427,
      "offerDate": "2024-11-27",
      "offerPrice": 111500,
      "status": "recorder",
      "isRebuilt": false,
      "address": "405 15TH TERRACE CIR NW, CENTER POINT AL",
      "city": "CENTER POINT",
      "state": "AL",
      "beds": null,
      "baths": null,
      "sqft": null,
      "lotSize": null,
      "lat": 33.626801,
      "lng": -86.693201
    },
    {
      "propertyId": null,
      "attomId": 144040297,
      "offerDate": "2024-11-20",
      "offerPrice": 70000,
      "status": "recorder",
      "isRebuilt": false,
      "address": "765 CROWNE RD, BIRMINGHAM AL",
      "city": "BIRMINGHAM",
      "state": "AL",
      "beds": null,
      "baths": null,
      "sqft": null,
      "lotSize": null,
      "lat": 33.506117,
      "lng": -86.927819
    },
    {
      "propertyId": null,
      "attomId": 142133438,
      "offerDate": "2024-11-19",
      "offerPrice": 95000,
      "status": "recorder",
      "isRebuilt": false,
      "address": "1513 BOBOLINK LN NE, CENTER POINT AL",
      "city": "CENTER POINT",
      "state": "AL",
      "beds": null,
      "baths": null,
      "sqft": null,
      "lotSize": null,
      "lat": 33.62427,
      "lng": -86.677609
    },
    {
      "propertyId": null,
      "attomId": 13867778,
      "offerDate": "2024-11-19",
      "offerPrice": 110000,
      "status": "recorder",
      "isRebuilt": false,
      "address": "208 BOXWOOD CIR, BIRMINGHAM AL",
      "city": "BIRMINGHAM",
      "state": "AL",
      "beds": null,
      "baths": null,
      "sqft": null,
      "lotSize": null,
      "lat": 33.599617,
      "lng": -86.711004
    },
    {
      "propertyId": null,
      "attomId": 197051235,
      "offerDate": "2024-11-19",
      "offerPrice": 91000,
      "status": "recorder",
      "isRebuilt": false,
      "address": "717 CARSON RD, BIRMINGHAM AL",
      "city": "BIRMINGHAM",
      "state": "AL",
      "beds": null,
      "baths": null,
      "sqft": null,
      "lotSize": null,
      "lat": 33.622074,
      "lng": -86.705948
    },
    {
      "propertyId": null,
      "attomId": 144679564,
      "offerDate": "2024-11-13",
      "offerPrice": 230000,
      "status": "recorder",
      "isRebuilt": false,
      "address": "3501 39TH PL N, BIRMINGHAM AL",
      "city": "BIRMINGHAM",
      "state": "AL",
      "beds": null,
      "baths": null,
      "sqft": null,
      "lotSize": null,
      "lat": 33.556394,
      "lng": -86.779894
    },
    {
      "propertyId": null,
      "attomId": 144766481,
      "offerDate": "2024-11-12",
      "offerPrice": 15000,
      "status": "recorder",
      "isRebuilt": false,
      "address": "1236 FRISCO ST, BIRMINGHAM AL",
      "city": "BIRMINGHAM",
      "state": "AL",
      "beds": null,
      "baths": null,
      "sqft": null,
      "lotSize": null,
      "lat": 33.499625,
      "lng": -86.919232
    },
    {
      "propertyId": null,
      "attomId": 203035971,
      "offerDate": "2024-11-12",
      "offerPrice": 110000,
      "status": "recorder",
      "isRebuilt": false,
      "address": "1324 47TH STREET ENSLEY, BIRMINGHAM AL",
      "city": "BIRMINGHAM",
      "state": "AL",
      "beds": null,
      "baths": null,
      "sqft": null,
      "lotSize": null,
      "lat": 33.486821,
      "lng": -86.89504
    },
    {
      "propertyId": null,
      "attomId": 186434802,
      "offerDate": "2024-10-30",
      "offerPrice": 75000,
      "status": "recorder",
      "isRebuilt": false,
      "address": "365 MIDWOOD AVE, BIRMINGHAM AL",
      "city": "BIRMINGHAM",
      "state": "AL",
      "beds": null,
      "baths": null,
      "sqft": null,
      "lotSize": null,
      "lat": 33.465226,
      "lng": -86.9053
    },
    {
      "propertyId": null,
      "attomId": 53552843,
      "offerDate": "2024-10-30",
      "offerPrice": 52000,
      "status": "recorder",
      "isRebuilt": false,
      "address": "120 94TH ST N, BIRMINGHAM AL",
      "city": "BIRMINGHAM",
      "state": "AL",
      "beds": null,
      "baths": null,
      "sqft": null,
      "lotSize": null,
      "lat": 33.58915,
      "lng": -86.715698
    },
    {
      "propertyId": null,
      "attomId": 22179327,
      "offerDate": "2024-10-22",
      "offerPrice": 100000,
      "status": "recorder",
      "isRebuilt": false,
      "address": "2400 2ND ST NW, CENTER POINT AL",
      "city": "CENTER POINT",
      "state": "AL",
      "beds": null,
      "baths": null,
      "sqft": null,
      "lotSize": null,
      "lat": 33.649717,
      "lng": -86.688781
    },
    {
      "propertyId": null,
      "attomId": 199948861,
      "offerDate": "2024-10-22",
      "offerPrice": 104000,
      "status": "recorder",
      "isRebuilt": false,
      "address": "2321 4TH ST NE, CENTER POINT AL",
      "city": "CENTER POINT",
      "state": "AL",
      "beds": null,
      "baths": null,
      "sqft": null,
      "lotSize": null,
      "lat": 33.647566,
      "lng": -86.674398
    },
    {
      "propertyId": null,
      "attomId": 10582034,
      "offerDate": "2024-10-22",
      "offerPrice": 68500,
      "status": "recorder",
      "isRebuilt": false,
      "address": "635 OAK CIR, BIRMINGHAM AL",
      "city": "BIRMINGHAM",
      "state": "AL",
      "beds": null,
      "baths": null,
      "sqft": null,
      "lotSize": null,
      "lat": 33.58189,
      "lng": -86.685083
    },
    {
      "propertyId": null,
      "attomId": 192758409,
      "offerDate": "2024-10-21",
      "offerPrice": 92000,
      "status": "recorder",
      "isRebuilt": false,
      "address": "217 13TH TER N, BIRMINGHAM AL",
      "city": "BIRMINGHAM",
      "state": "AL",
      "beds": null,
      "baths": null,
      "sqft": null,
      "lotSize": null,
      "lat": 33.526749,
      "lng": -86.833327
    },
    {
      "propertyId": null,
      "attomId": 11434718,
      "offerDate": "2024-10-21",
      "offerPrice": 105000,
      "status": "recorder",
      "isRebuilt": false,
      "address": "1600 1ST ST NW, CENTER POINT AL",
      "city": "CENTER POINT",
      "state": "AL",
      "beds": null,
      "baths": null,
      "sqft": null,
      "lotSize": null,
      "lat": 33.6282,
      "lng": -86.686932
    },
    {
      "propertyId": null,
      "attomId": 202327095,
      "offerDate": "2024-10-09",
      "offerPrice": 28000,
      "status": "recorder",
      "isRebuilt": false,
      "address": "1619 27TH STREET ENSLEY, BIRMINGHAM AL",
      "city": "BIRMINGHAM",
      "state": "AL",
      "beds": null,
      "baths": null,
      "sqft": null,
      "lotSize": null,
      "lat": 33.501895,
      "lng": -86.888255
    },
    {
      "propertyId": null,
      "attomId": 9720945,
      "offerDate": "2024-10-07",
      "offerPrice": 115000,
      "status": "recorder",
      "isRebuilt": false,
      "address": "408 13TH TER NW, CENTER POINT AL",
      "city": "CENTER POINT",
      "state": "AL",
      "beds": null,
      "baths": null,
      "sqft": null,
      "lotSize": null,
      "lat": 33.621772,
      "lng": -86.69399
    },
    {
      "propertyId": null,
      "attomId": 198012504,
      "offerDate": "2024-09-23",
      "offerPrice": 28500,
      "status": "recorder",
      "isRebuilt": false,
      "address": "4836 TERRACE S, BIRMINGHAM AL",
      "city": "BIRMINGHAM",
      "state": "AL",
      "beds": null,
      "baths": null,
      "sqft": null,
      "lotSize": null,
      "lat": 33.488411,
      "lng": -86.878808
    },
    {
      "propertyId": null,
      "attomId": 43945940,
      "offerDate": "2024-09-16",
      "offerPrice": 88000,
      "status": "recorder",
      "isRebuilt": false,
      "address": "209 CHEYENNE BLVD, BIRMINGHAM AL",
      "city": "BIRMINGHAM",
      "state": "AL",
      "beds": null,
      "baths": null,
      "sqft": null,
      "lotSize": null,
      "lat": 33.615238,
      "lng": -86.684741
    },
    {
      "propertyId": null,
      "attomId": 23673458,
      "offerDate": "2024-09-05",
      "offerPrice": 100000,
      "status": "recorder",
      "isRebuilt": false,
      "address": "7757 RUGBY AVE, BIRMINGHAM AL",
      "city": "BIRMINGHAM",
      "state": "AL",
      "beds": null,
      "baths": null,
      "sqft": null,
      "lotSize": null,
      "lat": 33.557087,
      "lng": -86.718732
    },
    {
      "propertyId": null,
      "attomId": 8078187,
      "offerDate": "2024-08-30",
      "offerPrice": 50000,
      "status": "recorder",
      "isRebuilt": false,
      "address": "1213 MAPLE ST, BIRMINGHAM AL",
      "city": "BIRMINGHAM",
      "state": "AL",
      "beds": null,
      "baths": null,
      "sqft": null,
      "lotSize": null,
      "lat": 33.576176,
      "lng": -86.77527
    },
    {
      "propertyId": null,
      "attomId": 149013259,
      "offerDate": "2024-08-21",
      "offerPrice": 82500,
      "status": "recorder",
      "isRebuilt": false,
      "address": "4100 PARK AVE SW, BIRMINGHAM AL",
      "city": "BIRMINGHAM",
      "state": "AL",
      "beds": null,
      "baths": null,
      "sqft": null,
      "lotSize": null,
      "lat": 33.450994,
      "lng": -86.898944
    },
    {
      "propertyId": null,
      "attomId": 144098630,
      "offerDate": "2024-08-21",
      "offerPrice": 87500,
      "status": "recorder",
      "isRebuilt": false,
      "address": "4338 49TH CT N, BIRMINGHAM AL",
      "city": "BIRMINGHAM",
      "state": "AL",
      "beds": null,
      "baths": null,
      "sqft": null,
      "lotSize": null,
      "lat": 33.571637,
      "lng": -86.771203
    },
    {
      "propertyId": null,
      "attomId": 30370680,
      "offerDate": "2024-08-21",
      "offerPrice": 65000,
      "status": "recorder",
      "isRebuilt": false,
      "address": "608 AVENUE V, BIRMINGHAM AL",
      "city": "BIRMINGHAM",
      "state": "AL",
      "beds": null,
      "baths": null,
      "sqft": null,
      "lotSize": null,
      "lat": 33.527237,
      "lng": -86.879959
    },
    {
      "propertyId": null,
      "attomId": 192784004,
      "offerDate": "2024-08-21",
      "offerPrice": 85000,
      "status": "recorder",
      "isRebuilt": false,
      "address": "109 FAIRFIELD BLVD, BIRMINGHAM AL",
      "city": "BIRMINGHAM",
      "state": "AL",
      "beds": null,
      "baths": null,
      "sqft": null,
      "lotSize": null,
      "lat": 33.46401,
      "lng": -86.941987
    },
    {
      "propertyId": null,
      "attomId": 188304361,
      "offerDate": "2024-08-16",
      "offerPrice": 60000,
      "status": "recorder",
      "isRebuilt": false,
      "address": "5621 TERRACE J, BIRMINGHAM AL",
      "city": "BIRMINGHAM",
      "state": "AL",
      "beds": null,
      "baths": null,
      "sqft": null,
      "lotSize": null,
      "lat": 33.479034,
      "lng": -86.899024
    },
    {
      "propertyId": null,
      "attomId": 54512005,
      "offerDate": "2024-08-16",
      "offerPrice": 69500,
      "status": "recorder",
      "isRebuilt": false,
      "address": "2204 CARLOS AVE SW, BIRMINGHAM AL",
      "city": "BIRMINGHAM",
      "state": "AL",
      "beds": null,
      "baths": null,
      "sqft": null,
      "lotSize": null,
      "lat": 33.465169,
      "lng": -86.873003
    },
    {
      "propertyId": null,
      "attomId": 10136268,
      "offerDate": "2024-08-12",
      "offerPrice": 50000,
      "status": "recorder",
      "isRebuilt": false,
      "address": "4745 COURT S, BIRMINGHAM AL",
      "city": "BIRMINGHAM",
      "state": "AL",
      "beds": null,
      "baths": null,
      "sqft": null,
      "lotSize": null,
      "lat": 33.489244,
      "lng": -86.880396
    },
    {
      "propertyId": null,
      "attomId": 12770210,
      "offerDate": "2024-08-05",
      "offerPrice": 38500,
      "status": "recorder",
      "isRebuilt": false,
      "address": "2824 25TH STREET ENSLEY, BIRMINGHAM AL",
      "city": "BIRMINGHAM",
      "state": "AL",
      "beds": null,
      "baths": null,
      "sqft": null,
      "lotSize": null,
      "lat": 33.504435,
      "lng": -86.868973
    },
    {
      "propertyId": null,
      "attomId": 151690093,
      "offerDate": "2024-07-22",
      "offerPrice": 50000,
      "status": "recorder",
      "isRebuilt": false,
      "address": "4136 41ST AVE N, BIRMINGHAM AL",
      "city": "BIRMINGHAM",
      "state": "AL",
      "beds": null,
      "baths": null,
      "sqft": null,
      "lotSize": null,
      "lat": 33.563048,
      "lng": -86.775099
    },
    {
      "propertyId": null,
      "attomId": 151433446,
      "offerDate": "2024-07-17",
      "offerPrice": 75000,
      "status": "recorder",
      "isRebuilt": false,
      "address": "1401 43RD STREET ENSLEY, BIRMINGHAM AL",
      "city": "BIRMINGHAM",
      "state": "AL",
      "beds": null,
      "baths": null,
      "sqft": null,
      "lotSize": null,
      "lat": 33.490138,
      "lng": -86.89372
    },
    {
      "propertyId": null,
      "attomId": 3648932,
      "offerDate": "2024-07-11",
      "offerPrice": 63000,
      "status": "recorder",
      "isRebuilt": false,
      "address": "5721 MONTE SANO RD, BIRMINGHAM AL",
      "city": "BIRMINGHAM",
      "state": "AL",
      "beds": null,
      "baths": null,
      "sqft": null,
      "lotSize": null,
      "lat": 33.478137,
      "lng": -86.900482
    },
    {
      "propertyId": null,
      "attomId": 46084942,
      "offerDate": "2024-07-11",
      "offerPrice": 50000,
      "status": "recorder",
      "isRebuilt": false,
      "address": "508 WESTFIELD DR, FAIRFIELD AL",
      "city": "FAIRFIELD",
      "state": "AL",
      "beds": null,
      "baths": null,
      "sqft": null,
      "lotSize": null,
      "lat": 33.459005,
      "lng": -86.93635
    },
    {
      "propertyId": null,
      "attomId": 206245663,
      "offerDate": "2024-07-03",
      "offerPrice": 63500,
      "status": "recorder",
      "isRebuilt": false,
      "address": "2832 23RD STREET ENSLEY, BIRMINGHAM AL",
      "city": "BIRMINGHAM",
      "state": "AL",
      "beds": null,
      "baths": null,
      "sqft": null,
      "lotSize": null,
      "lat": 33.506467,
      "lng": -86.868516
    },
    {
      "propertyId": null,
      "attomId": 201759554,
      "offerDate": "2024-07-03",
      "offerPrice": 63500,
      "status": "recorder",
      "isRebuilt": false,
      "address": "3057 53RD CT N, BIRMINGHAM AL",
      "city": "BIRMINGHAM",
      "state": "AL",
      "beds": null,
      "baths": null,
      "sqft": null,
      "lotSize": null,
      "lat": 33.578805,
      "lng": -86.806798
    },
    {
      "propertyId": null,
      "attomId": 8635600,
      "offerDate": "2024-07-03",
      "offerPrice": 21500,
      "status": "recorder",
      "isRebuilt": false,
      "address": "1233 FULTON AVE, BIRMINGHAM AL",
      "city": "BIRMINGHAM",
      "state": "AL",
      "beds": null,
      "baths": null,
      "sqft": null,
      "lotSize": null,
      "lat": 33.495244,
      "lng": -86.854833
    },
    {
      "propertyId": null,
      "attomId": 1427813,
      "offerDate": "2024-07-03",
      "offerPrice": 83000,
      "status": "recorder",
      "isRebuilt": false,
      "address": "957 FIVE MILE RD, BIRMINGHAM AL",
      "city": "BIRMINGHAM",
      "state": "AL",
      "beds": null,
      "baths": null,
      "sqft": null,
      "lotSize": null,
      "lat": 33.60517,
      "lng": -86.699878
    },
    {
      "propertyId": null,
      "attomId": 188083030,
      "offerDate": "2024-07-03",
      "offerPrice": 40000,
      "status": "recorder",
      "isRebuilt": false,
      "address": "933 JACKSON BLVD, BIRMINGHAM AL",
      "city": "BIRMINGHAM",
      "state": "AL",
      "beds": null,
      "baths": null,
      "sqft": null,
      "lotSize": null,
      "lat": 33.575608,
      "lng": -86.779107
    },
    {
      "propertyId": null,
      "attomId": 192771424,
      "offerDate": "2024-06-25",
      "offerPrice": 45000,
      "status": "recorder",
      "isRebuilt": false,
      "address": "5600 TERRACE J, BIRMINGHAM AL",
      "city": "BIRMINGHAM",
      "state": "AL",
      "beds": null,
      "baths": null,
      "sqft": null,
      "lotSize": null,
      "lat": 33.479663,
      "lng": -86.899565
    },
    {
      "propertyId": null,
      "attomId": 150030993,
      "offerDate": "2024-06-18",
      "offerPrice": 80000,
      "status": "recorder",
      "isRebuilt": false,
      "address": "1701 4TH AVE W, BIRMINGHAM AL",
      "city": "BIRMINGHAM",
      "state": "AL",
      "beds": null,
      "baths": null,
      "sqft": null,
      "lotSize": null,
      "lat": 33.505792,
      "lng": -86.864597
    },
    {
      "propertyId": null,
      "attomId": 18641944,
      "offerDate": "2024-06-18",
      "offerPrice": 63000,
      "status": "recorder",
      "isRebuilt": false,
      "address": "1421 MONTVIEW RD, BIRMINGHAM AL",
      "city": "BIRMINGHAM",
      "state": "AL",
      "beds": null,
      "baths": null,
      "sqft": null,
      "lotSize": null,
      "lat": 33.473405,
      "lng": -86.892739
    },
    {
      "propertyId": null,
      "attomId": 1782806,
      "offerDate": "2024-06-18",
      "offerPrice": 55000,
      "status": "recorder",
      "isRebuilt": false,
      "address": "5503 COURT P, BIRMINGHAM AL",
      "city": "BIRMINGHAM",
      "state": "AL",
      "beds": null,
      "baths": null,
      "sqft": null,
      "lotSize": null,
      "lat": 33.480127,
      "lng": -86.888364
    },
    {
      "propertyId": null,
      "attomId": 148518414,
      "offerDate": "2024-06-11",
      "offerPrice": 65000,
      "status": "recorder",
      "isRebuilt": false,
      "address": "226 68TH ST N, BIRMINGHAM AL",
      "city": "BIRMINGHAM",
      "state": "AL",
      "beds": null,
      "baths": null,
      "sqft": null,
      "lotSize": null,
      "lat": 33.55295,
      "lng": -86.740728
    },
    {
      "propertyId": null,
      "attomId": 147708613,
      "offerDate": "2024-06-06",
      "offerPrice": 65000,
      "status": "recorder",
      "isRebuilt": false,
      "address": "745 70TH PL S, BIRMINGHAM AL",
      "city": "BIRMINGHAM",
      "state": "AL",
      "beds": null,
      "baths": null,
      "sqft": null,
      "lotSize": null,
      "lat": 33.548458,
      "lng": -86.724636
    },
    {
      "propertyId": null,
      "attomId": 155177862,
      "offerDate": "2024-06-06",
      "offerPrice": 79900,
      "status": "recorder",
      "isRebuilt": false,
      "address": "1628 52ND STREET ENSLEY, BIRMINGHAM AL",
      "city": "BIRMINGHAM",
      "state": "AL",
      "beds": null,
      "baths": null,
      "sqft": null,
      "lotSize": null,
      "lat": 33.482408,
      "lng": -86.887935
    },
    {
      "propertyId": null,
      "attomId": 187324283,
      "offerDate": "2024-06-06",
      "offerPrice": 87500,
      "status": "recorder",
      "isRebuilt": false,
      "address": "1200 14TH PL SW, BIRMINGHAM AL",
      "city": "BIRMINGHAM",
      "state": "AL",
      "beds": null,
      "baths": null,
      "sqft": null,
      "lotSize": null,
      "lat": 33.485374,
      "lng": -86.851172
    },
    {
      "propertyId": null,
      "attomId": 144766219,
      "offerDate": "2024-06-06",
      "offerPrice": 7800,
      "status": "recorder",
      "isRebuilt": false,
      "address": "1226 FRISCO ST, BIRMINGHAM AL",
      "city": "BIRMINGHAM",
      "state": "AL",
      "beds": null,
      "baths": null,
      "sqft": null,
      "lotSize": null,
      "lat": 33.500002,
      "lng": -86.919228
    },
    {
      "propertyId": null,
      "attomId": 10459211,
      "offerDate": "2024-06-06",
      "offerPrice": 80000,
      "status": "recorder",
      "isRebuilt": false,
      "address": "225 PINEWOOD AVE, BIRMINGHAM AL",
      "city": "BIRMINGHAM",
      "state": "AL",
      "beds": null,
      "baths": null,
      "sqft": null,
      "lotSize": null,
      "lat": 33.460952,
      "lng": -86.913427
    },
    {
      "propertyId": null,
      "attomId": 1287911,
      "offerDate": "2024-04-16",
      "offerPrice": 35000,
      "status": "recorder",
      "isRebuilt": false,
      "address": "806 10TH AVE, BIRMINGHAM AL",
      "city": "BIRMINGHAM",
      "state": "AL",
      "beds": null,
      "baths": null,
      "sqft": null,
      "lotSize": null,
      "lat": 33.45265,
      "lng": -86.943395
    },
    {
      "propertyId": null,
      "attomId": 155352876,
      "offerDate": "2024-04-04",
      "offerPrice": 59000,
      "status": "recorder",
      "isRebuilt": false,
      "address": "5528 MADISON DR, BIRMINGHAM AL",
      "city": "BIRMINGHAM",
      "state": "AL",
      "beds": null,
      "baths": null,
      "sqft": null,
      "lotSize": null,
      "lat": 33.441275,
      "lng": -86.927858
    },
    {
      "propertyId": null,
      "attomId": 43567822,
      "offerDate": "2024-03-28",
      "offerPrice": 47000,
      "status": "recorder",
      "isRebuilt": false,
      "address": "3840 40TH AVE N, BIRMINGHAM AL",
      "city": "BIRMINGHAM",
      "state": "AL",
      "beds": null,
      "baths": null,
      "sqft": null,
      "lotSize": null,
      "lat": 33.562363,
      "lng": -86.781399
    },
    {
      "propertyId": null,
      "attomId": 7409944,
      "offerDate": "2024-03-27",
      "offerPrice": 59000,
      "status": "recorder",
      "isRebuilt": false,
      "address": "3517 ELLIS AVE SW, BIRMINGHAM AL",
      "city": "BIRMINGHAM",
      "state": "AL",
      "beds": null,
      "baths": null,
      "sqft": null,
      "lotSize": null,
      "lat": 33.458626,
      "lng": -86.891067
    },
    {
      "propertyId": null,
      "attomId": 20820662,
      "offerDate": "2024-03-12",
      "offerPrice": 92500,
      "status": "recorder",
      "isRebuilt": false,
      "address": "1761 48TH STREET ENSLEY, BIRMINGHAM AL",
      "city": "BIRMINGHAM",
      "state": "AL",
      "beds": null,
      "baths": null,
      "sqft": null,
      "lotSize": null,
      "lat": 33.485562,
      "lng": -86.884701
    },
    {
      "propertyId": null,
      "attomId": 204019204,
      "offerDate": "2024-03-12",
      "offerPrice": 50000,
      "status": "recorder",
      "isRebuilt": false,
      "address": "408 4TH ST, FORESTDALE AL",
      "city": "FORESTDALE",
      "state": "AL",
      "beds": null,
      "baths": null,
      "sqft": null,
      "lotSize": null,
      "lat": 33.52991485595703,
      "lng": -86.858374
    },
    {
      "propertyId": null,
      "attomId": 9650380,
      "offerDate": "2024-03-11",
      "offerPrice": 23000,
      "status": "recorder",
      "isRebuilt": false,
      "address": "1540 42ND STREET ENSLEY, BIRMINGHAM AL",
      "city": "BIRMINGHAM",
      "state": "AL",
      "beds": null,
      "baths": null,
      "sqft": null,
      "lotSize": null,
      "lat": 33.491585,
      "lng": -86.890114
    },
    {
      "propertyId": null,
      "attomId": 196239120,
      "offerDate": "2024-03-06",
      "offerPrice": 62000,
      "status": "recorder",
      "isRebuilt": false,
      "address": "1905 WEATHERLY AVE, BIRMINGHAM AL",
      "city": "BIRMINGHAM",
      "state": "AL",
      "beds": null,
      "baths": null,
      "sqft": null,
      "lotSize": null,
      "lat": 33.594036,
      "lng": -86.744456
    },
    {
      "propertyId": null,
      "attomId": 148383364,
      "offerDate": "2024-03-05",
      "offerPrice": 44000,
      "status": "recorder",
      "isRebuilt": false,
      "address": "3301 HILLCREST AVE, BIRMINGHAM AL",
      "city": "BIRMINGHAM",
      "state": "AL",
      "beds": null,
      "baths": null,
      "sqft": null,
      "lotSize": null,
      "lat": 33.540423,
      "lng": -86.943755
    },
    {
      "propertyId": null,
      "attomId": 155279042,
      "offerDate": "2024-03-05",
      "offerPrice": 297500,
      "status": "recorder",
      "isRebuilt": false,
      "address": "407 AVENUE U, BIRMINGHAM AL",
      "city": "BIRMINGHAM",
      "state": "AL",
      "beds": null,
      "baths": null,
      "sqft": null,
      "lotSize": null,
      "lat": 33.530279,
      "lng": -86.8806
    },
    {
      "propertyId": null,
      "attomId": 190233237,
      "offerDate": "2024-03-01",
      "offerPrice": 20000,
      "status": "recorder",
      "isRebuilt": false,
      "address": "915 AVENUE E, BIRMINGHAM AL",
      "city": "BIRMINGHAM",
      "state": "AL",
      "beds": null,
      "baths": null,
      "sqft": null,
      "lotSize": null,
      "lat": 33.523172,
      "lng": -86.88857
    },
    {
      "propertyId": null,
      "attomId": 197146320,
      "offerDate": "2024-02-28",
      "offerPrice": 236500,
      "status": "recorder",
      "isRebuilt": false,
      "address": "604 AVENUE U, BIRMINGHAM AL",
      "city": "BIRMINGHAM",
      "state": "AL",
      "beds": null,
      "baths": null,
      "sqft": null,
      "lotSize": null,
      "lat": 33.527374,
      "lng": -86.881114
    },
    {
      "propertyId": null,
      "attomId": 143057722,
      "offerDate": "2024-02-01",
      "offerPrice": 52000,
      "status": "recorder",
      "isRebuilt": false,
      "address": "623 LAMBERTH DR, ADAMSVILLE AL",
      "city": "ADAMSVILLE",
      "state": "AL",
      "beds": null,
      "baths": null,
      "sqft": null,
      "lotSize": null,
      "lat": 33.595815,
      "lng": -86.967022
    }
  ]
}