{
  "investor": {
    "id": "298dc652-5d34-47d7-8927-5d9db9f0dc04",
    "name": "Jared Christensen",
    "email": "jared2438@gmail.com",
    "phone": "+1 (615) 476-8269",
    "totalWon": 3,
    "totalBids": 8,
    "ytdWon": 0,
    "ytdBids": 0,
    "entities": [
      "BLACK LIGHT PROPERTIES LLC",
      "JARED CHRISTENSEN"
    ]
  },
  "stats": {
    "totalTransactions2025": 17,
    "rebuiltTransactions": 3,
    "recorderTransactions": 17,
    "quarterlyStats": {
      "2025-Q1": {
        "rebuilt": 0,
        "total": 2
      },
      "2025-Q2": {
        "rebuilt": 1,
        "total": 3
      },
      "2025-Q3": {
        "rebuilt": 1,
        "total": 12
      },
      "2025-Q4": {
        "rebuilt": 0,
        "total": 0
      },
      "2026-Q1": {
        "rebuilt": 0,
        "total": 2
      }
    }
  },
  "properties": [
    {
      "propertyId": "3a7c8ae3-5070-4a96-b329-7a4fac7f2b90",
      "attomId": null,
      "offerDate": "2024-05-05T05:00:00.000Z",
      "offerPrice": 68500,
      "status": "done",
      "isRebuilt": true,
      "address": null,
      "city": null,
      "state": null,
      "beds": null,
      "baths": null,
      "sqft": null,
      "lotSize": null,
      "lat": null,
      "lng": null
    },
    {
      "propertyId": "0197a7c3-ff7f-783d-8158-0c99f3293206",
      "attomId": null,
      "offerDate": "2025-06-28T05:00:00.000Z",
      "offerPrice": 60000,
      "status": "done",
      "isRebuilt": true,
      "address": null,
      "city": null,
      "state": null,
      "beds": null,
      "baths": null,
      "sqft": null,
      "lotSize": null,
      "lat": null,
      "lng": null
    },
    {
      "propertyId": "019837e0-57b4-7c91-be7d-e5a921f70acf",
      "attomId": 194542665,
      "offerDate": "2025-07-28T05:00:00.000Z",
      "offerPrice": 41000,
      "status": "done",
      "isRebuilt": true,
      "address": "355 DELLER ST, LAWRENCEBURG TN",
      "city": "LAWRENCEBURG",
      "state": "TN",
      "beds": 0,
      "baths": 1,
      "sqft": 848,
      "lotSize": 0.1893939,
      "lat": 35.24447,
      "lng": -87.339236
    },
    {
      "propertyId": null,
      "attomId": 17678694,
      "offerDate": "2026-01-13T06:00:00.000Z",
      "offerPrice": 0,
      "status": "recorded",
      "isRebuilt": false,
      "address": "1407 BECKHAM AVE, LAWRENCEBURG TN",
      "city": "LAWRENCEBURG",
      "state": "TN",
      "beds": 0,
      "baths": 1,
      "sqft": 1373,
      "lotSize": 0.2668733,
      "lat": 35.259601,
      "lng": -87.339366,
      "entity": "BLACK LIGHT PROPERTIES LLC"
    },
    {
      "propertyId": null,
      "attomId": 147069741,
      "offerDate": "2026-01-13T06:00:00.000Z",
      "offerPrice": 0,
      "status": "recorded",
      "isRebuilt": false,
      "address": "419 PALMER ST, LAWRENCEBURG TN",
      "city": "LAWRENCEBURG",
      "state": "TN",
      "beds": 0,
      "baths": 1,
      "sqft": 912,
      "lotSize": 0.2995868,
      "lat": 35.246318,
      "lng": -87.341905,
      "entity": "BLACK LIGHT PROPERTIES LLC"
    },
    {
      "propertyId": null,
      "attomId": 44506619,
      "offerDate": "2025-07-25T05:00:00.000Z",
      "offerPrice": 0,
      "status": "recorded",
      "isRebuilt": false,
      "address": "134 CHURCH ST, CENTERVILLE TN",
      "city": "CENTERVILLE",
      "state": "TN",
      "beds": 0,
      "baths": 1,
      "sqft": 1946,
      "lotSize": 0.6199954,
      "lat": 35.777857,
      "lng": -87.461534,
      "entity": "BLACK LIGHT PROPERTIES LLC"
    },
    {
      "propertyId": null,
      "attomId": 193273425,
      "offerDate": "2025-07-25T05:00:00.000Z",
      "offerPrice": 0,
      "status": "recorded",
      "isRebuilt": false,
      "address": "1815 HIGHWAY 100, CENTERVILLE TN",
      "city": "CENTERVILLE",
      "state": "TN",
      "beds": 0,
      "baths": 0.5,
      "sqft": 2448,
      "lotSize": 0.2754821,
      "lat": 35.835651,
      "lng": -87.430135,
      "entity": "BLACK LIGHT PROPERTIES LLC"
    },
    {
      "propertyId": null,
      "attomId": 200098978,
      "offerDate": "2025-07-25T05:00:00.000Z",
      "offerPrice": 0,
      "status": "recorded",
      "isRebuilt": false,
      "address": "1011 DALTON ST, COLUMBIA TN",
      "city": "COLUMBIA",
      "state": "TN",
      "beds": 0,
      "baths": 1,
      "sqft": 880,
      "lotSize": 0.1764233,
      "lat": 35.610028,
      "lng": -87.022255,
      "entity": "BLACK LIGHT PROPERTIES LLC"
    },
    {
      "propertyId": null,
      "attomId": 195832047,
      "offerDate": "2025-07-25T05:00:00.000Z",
      "offerPrice": 0,
      "status": "recorded",
      "isRebuilt": false,
      "address": "432 4TH ST, LAWRENCEBURG TN",
      "city": "LAWRENCEBURG",
      "state": "TN",
      "beds": 0,
      "baths": 1,
      "sqft": 840,
      "lotSize": 0.1721763,
      "lat": 35.246631,
      "lng": -87.322957,
      "entity": "BLACK LIGHT PROPERTIES LLC"
    },
    {
      "propertyId": null,
      "attomId": 47265866,
      "offerDate": "2025-07-25T05:00:00.000Z",
      "offerPrice": 0,
      "status": "recorded",
      "isRebuilt": false,
      "address": "532 6TH ST, LAWRENCEBURG TN",
      "city": "LAWRENCEBURG",
      "state": "TN",
      "beds": 0,
      "baths": 1,
      "sqft": 1092,
      "lotSize": 0.1721763,
      "lat": 35.248254,
      "lng": -87.319166,
      "entity": "BLACK LIGHT PROPERTIES LLC"
    },
    {
      "propertyId": null,
      "attomId": 196652019,
      "offerDate": "2025-07-25T05:00:00.000Z",
      "offerPrice": 0,
      "status": "recorded",
      "isRebuilt": false,
      "address": "204 HALLS ALY, MT PLEASANT TN",
      "city": "MT PLEASANT",
      "state": "TN",
      "beds": 0,
      "baths": 1,
      "sqft": 962,
      "lotSize": 0.5123967,
      "lat": 35.529991,
      "lng": -87.21173,
      "entity": "BLACK LIGHT PROPERTIES LLC"
    },
    {
      "propertyId": null,
      "attomId": 202179752,
      "offerDate": "2025-07-25T05:00:00.000Z",
      "offerPrice": 0,
      "status": "recorded",
      "isRebuilt": false,
      "address": "222 E TAYLOR ST # 226, LAWRENCEBURG TN",
      "city": "LAWRENCEBURG",
      "state": "TN",
      "beds": 0,
      "baths": 1,
      "sqft": 810,
      "lotSize": 0.2887052,
      "lat": 35.239216,
      "lng": -87.33344,
      "entity": "BLACK LIGHT PROPERTIES LLC"
    },
    {
      "propertyId": null,
      "attomId": 188994804,
      "offerDate": "2025-07-25T05:00:00.000Z",
      "offerPrice": 0,
      "status": "recorded",
      "isRebuilt": false,
      "address": "122 MURPHREE AVE, CENTERVILLE TN",
      "city": "CENTERVILLE",
      "state": "TN",
      "beds": 0,
      "baths": 1,
      "sqft": 996,
      "lotSize": 0,
      "lat": 35.781195,
      "lng": -87.462857,
      "entity": "BLACK LIGHT PROPERTIES LLC"
    },
    {
      "propertyId": null,
      "attomId": 3662274,
      "offerDate": "2025-07-22T05:00:00.000Z",
      "offerPrice": 50000,
      "status": "recorded",
      "isRebuilt": false,
      "address": "1098 N MAIN ST, MT PLEASANT TN",
      "city": "MT PLEASANT",
      "state": "TN",
      "beds": 0,
      "baths": 1,
      "sqft": 872,
      "lotSize": 0.2479339,
      "lat": 35.55142,
      "lng": -87.191178,
      "entity": "BLACK LIGHT PROPERTIES LLC"
    },
    {
      "propertyId": null,
      "attomId": 156850970,
      "offerDate": "2025-07-14T05:00:00.000Z",
      "offerPrice": 1260000,
      "status": "recorded",
      "isRebuilt": false,
      "address": "1931 ROANOKE AVE, TUSTIN CA",
      "city": "TUSTIN",
      "state": "CA",
      "beds": 3,
      "baths": 2,
      "sqft": 1268,
      "lotSize": 0.1147842,
      "lat": 33.723235,
      "lng": -117.815939,
      "entity": "JARED CHRISTENSEN"
    },
    {
      "propertyId": null,
      "attomId": 289596397,
      "offerDate": "2025-07-08T05:00:00.000Z",
      "offerPrice": 9500,
      "status": "recorded",
      "isRebuilt": false,
      "address": "6923 ABBEY LN, STANWOOD MI",
      "city": "STANWOOD",
      "state": "MI",
      "beds": 0,
      "baths": null,
      "sqft": 0,
      "lotSize": 0,
      "lat": 43.567115,
      "lng": -85.302258,
      "entity": "JARED CHRISTENSEN"
    },
    {
      "propertyId": null,
      "attomId": 310019033,
      "offerDate": "2025-05-22T05:00:00.000Z",
      "offerPrice": 202500,
      "status": "recorded",
      "isRebuilt": false,
      "address": "4873 TIMBER HILLS DR, HARSHAW WI",
      "city": "HARSHAW",
      "state": "WI",
      "beds": 0,
      "baths": null,
      "sqft": 0,
      "lotSize": 1.3,
      "lat": 45.701326,
      "lng": -89.713668,
      "entity": "JARED CHRISTENSEN"
    },
    {
      "propertyId": null,
      "attomId": 3662269,
      "offerDate": "2025-04-01T05:00:00.000Z",
      "offerPrice": 0,
      "status": "recorded",
      "isRebuilt": false,
      "address": "1109 N MAIN ST, MT PLEASANT TN",
      "city": "MT PLEASANT",
      "state": "TN",
      "beds": 0,
      "baths": 1,
      "sqft": 1344,
      "lotSize": 0.3555556,
      "lat": 35.552461,
      "lng": -87.190579,
      "entity": "BLACK LIGHT PROPERTIES LLC"
    },
    {
      "propertyId": null,
      "attomId": 217808297,
      "offerDate": "2025-01-24T06:00:00.000Z",
      "offerPrice": 44300,
      "status": "recorded",
      "isRebuilt": false,
      "address": "1950 N PIATT AVE, WICHITA KS",
      "city": "WICHITA",
      "state": "KS",
      "beds": 3,
      "baths": 1,
      "sqft": 825,
      "lotSize": 0.15,
      "lat": 37.718736,
      "lng": -97.312421,
      "entity": "JARED CHRISTENSEN"
    },
    {
      "propertyId": null,
      "attomId": 217796221,
      "offerDate": "2025-01-24T06:00:00.000Z",
      "offerPrice": 40200,
      "status": "recorded",
      "isRebuilt": false,
      "address": "724 N DOUGHERTY AVE, WICHITA KS",
      "city": "WICHITA",
      "state": "KS",
      "beds": 1,
      "baths": 1,
      "sqft": 528,
      "lotSize": 0.4399908,
      "lat": 37.695809,
      "lng": -97.39408,
      "entity": "JARED CHRISTENSEN"
    }
  ]
}