{
  "investor": {
    "id": "2e7f2a51-8c24-4095-9500-1b95d3b4a88b",
    "name": "Todd Simpson",
    "email": "tsimpson@jatoil.com",
    "phone": "+1 (256) 997-6757",
    "totalWon": 6,
    "totalBids": 18,
    "ytdWon": 0,
    "ytdBids": 0,
    "entities": [
      "simpson property llc"
    ]
  },
  "stats": {
    "totalTransactions2025": 18,
    "rebuiltTransactions": 0,
    "recorderTransactions": 19,
    "quarterlyStats": {
      "2025-Q1": {
        "rebuilt": 0,
        "total": 9
      },
      "2025-Q2": {
        "rebuilt": 0,
        "total": 3
      },
      "2025-Q3": {
        "rebuilt": 0,
        "total": 2
      },
      "2025-Q4": {
        "rebuilt": 0,
        "total": 4
      },
      "2026-Q1": {
        "rebuilt": 0,
        "total": 1
      }
    }
  },
  "properties": [
    {
      "propertyId": null,
      "attomId": 290535538,
      "offerDate": "2026-01-14T06:00:00.000Z",
      "offerPrice": 108500,
      "status": "recorded",
      "isRebuilt": false,
      "address": "1501 GODFREY AVE NE, FORT PAYNE AL",
      "city": "FORT PAYNE",
      "state": "AL",
      "beds": 0,
      "baths": 1,
      "sqft": 780,
      "lotSize": 0.4300046,
      "lat": 34.4204037,
      "lng": -85.7319887,
      "entity": "SIMPSON PROPERTY LLC"
    },
    {
      "propertyId": null,
      "attomId": 197851938,
      "offerDate": "2025-11-24T06:00:00.000Z",
      "offerPrice": 125000,
      "status": "recorded",
      "isRebuilt": false,
      "address": "104 PELL ST, ALBERTVILLE AL",
      "city": "ALBERTVILLE",
      "state": "AL",
      "beds": 0,
      "baths": 1,
      "sqft": 1270,
      "lotSize": 0.6864096,
      "lat": 34.2670879,
      "lng": -86.1881461,
      "entity": "SIMPSON PROPERTY LLC"
    },
    {
      "propertyId": null,
      "attomId": 290535262,
      "offerDate": "2025-10-30T05:00:00.000Z",
      "offerPrice": 115000,
      "status": "recorded",
      "isRebuilt": false,
      "address": "109 18TH ST NW, FORT PAYNE AL",
      "city": "FORT PAYNE",
      "state": "AL",
      "beds": 0,
      "baths": 1,
      "sqft": 1169,
      "lotSize": 0,
      "lat": 34.457484,
      "lng": -85.7071059,
      "entity": "SIMPSON PROPERTY LLC"
    },
    {
      "propertyId": null,
      "attomId": 290516059,
      "offerDate": "2025-10-21T05:00:00.000Z",
      "offerPrice": 75500,
      "status": "recorded",
      "isRebuilt": false,
      "address": "656 CLARK AVE NE, FORT PAYNE AL",
      "city": "FORT PAYNE",
      "state": "AL",
      "beds": 0,
      "baths": 1,
      "sqft": 776,
      "lotSize": 0,
      "lat": 34.4537709,
      "lng": -85.7045176,
      "entity": "SIMPSON PROPERTY LLC"
    },
    {
      "propertyId": null,
      "attomId": 197983913,
      "offerDate": "2025-10-03T05:00:00.000Z",
      "offerPrice": 130000,
      "status": "recorded",
      "isRebuilt": false,
      "address": "168 GOODWIN RD, ALBERTVILLE AL",
      "city": "ALBERTVILLE",
      "state": "AL",
      "beds": 0,
      "baths": 1,
      "sqft": 1040,
      "lotSize": 1.5,
      "lat": null,
      "lng": null,
      "entity": "SIMPSON PROPERTY LLC"
    },
    {
      "propertyId": null,
      "attomId": 290363434,
      "offerDate": "2025-08-25T05:00:00.000Z",
      "offerPrice": 0,
      "status": "recorded",
      "isRebuilt": false,
      "address": "111 PINE ST, CENTRE AL",
      "city": "CENTRE",
      "state": "AL",
      "beds": 0,
      "baths": null,
      "sqft": 660,
      "lotSize": 0,
      "lat": 41.0012783,
      "lng": -77.5477992,
      "entity": "SIMPSON PROPERTY LLC"
    },
    {
      "propertyId": null,
      "attomId": 188846195,
      "offerDate": "2025-07-03T05:00:00.000Z",
      "offerPrice": 119900,
      "status": "recorded",
      "isRebuilt": false,
      "address": "902 ADAMS ST, BOAZ AL",
      "city": "BOAZ",
      "state": "AL",
      "beds": 0,
      "baths": 1,
      "sqft": 1180,
      "lotSize": 0.3787879,
      "lat": 34.2109803,
      "lng": -86.1622364,
      "entity": "SIMPSON PROPERTY LLC"
    },
    {
      "propertyId": null,
      "attomId": 290364406,
      "offerDate": "2025-06-02T05:00:00.000Z",
      "offerPrice": 70000,
      "status": "recorded",
      "isRebuilt": false,
      "address": "1201 E MAIN ST, CENTRE AL",
      "city": "CENTRE",
      "state": "AL",
      "beds": 0,
      "baths": null,
      "sqft": 1376,
      "lotSize": 0.1699954,
      "lat": 40.9320028,
      "lng": -111.879039,
      "entity": "SIMPSON PROPERTY LLC"
    },
    {
      "propertyId": null,
      "attomId": 199369336,
      "offerDate": "2025-05-28T05:00:00.000Z",
      "offerPrice": 108000,
      "status": "recorded",
      "isRebuilt": false,
      "address": "161 2ND ST SW, ARAB AL",
      "city": "ARAB",
      "state": "AL",
      "beds": 0,
      "baths": 1,
      "sqft": 1176,
      "lotSize": 0.2527089,
      "lat": null,
      "lng": null,
      "entity": "SIMPSON PROPERTY LLC"
    },
    {
      "propertyId": null,
      "attomId": 290541590,
      "offerDate": "2025-04-02T05:00:00.000Z",
      "offerPrice": 28515,
      "status": "recorded",
      "isRebuilt": false,
      "address": "90 COUNTY ROAD 187, DAWSON AL",
      "city": "DAWSON",
      "state": "AL",
      "beds": 0,
      "baths": 1,
      "sqft": 941,
      "lotSize": 2.4000001,
      "lat": null,
      "lng": null,
      "entity": "SIMPSON PROPERTY LLC"
    },
    {
      "propertyId": null,
      "attomId": 290527873,
      "offerDate": "2025-02-18T06:00:00.000Z",
      "offerPrice": 137000,
      "status": "recorded",
      "isRebuilt": false,
      "address": "2302 GRAND AVE NW, FORT PAYNE AL",
      "city": "FORT PAYNE",
      "state": "AL",
      "beds": 0,
      "baths": 1,
      "sqft": 1512,
      "lotSize": 0,
      "lat": 34.4015222,
      "lng": -85.7598772,
      "entity": "SIMPSON PROPERTY LLC"
    },
    {
      "propertyId": null,
      "attomId": 290527873,
      "offerDate": "2025-02-18T06:00:00.000Z",
      "offerPrice": 137000,
      "status": "recorded",
      "isRebuilt": false,
      "address": "2302 GRAND AVE NW, FORT PAYNE AL",
      "city": "FORT PAYNE",
      "state": "AL",
      "beds": 0,
      "baths": 1,
      "sqft": 1512,
      "lotSize": 0,
      "lat": 34.4015222,
      "lng": -85.7598772,
      "entity": "SIMPSON PROPERTY LLC"
    },
    {
      "propertyId": null,
      "attomId": 193169121,
      "offerDate": "2025-02-11T06:00:00.000Z",
      "offerPrice": 89000,
      "status": "recorded",
      "isRebuilt": false,
      "address": "410 CHEROKEE ST, BOAZ AL",
      "city": "BOAZ",
      "state": "AL",
      "beds": 0,
      "baths": 1,
      "sqft": 772,
      "lotSize": 0.1119146,
      "lat": 34.2017484,
      "lng": -86.1572987,
      "entity": "SIMPSON PROPERTY LLC"
    },
    {
      "propertyId": null,
      "attomId": 290527143,
      "offerDate": "2025-02-03T06:00:00.000Z",
      "offerPrice": 100000,
      "status": "recorded",
      "isRebuilt": false,
      "address": "5315 OAKHILL RD NE, FORT PAYNE AL",
      "city": "FORT PAYNE",
      "state": "AL",
      "beds": 0,
      "baths": 1,
      "sqft": 1195,
      "lotSize": 1,
      "lat": null,
      "lng": null,
      "entity": "SIMPSON PROPERTY LLC"
    },
    {
      "propertyId": null,
      "attomId": 188221035,
      "offerDate": "2025-01-23T06:00:00.000Z",
      "offerPrice": 125000,
      "status": "recorded",
      "isRebuilt": false,
      "address": "407 PEACH AVE, ALBERTVILLE AL",
      "city": "ALBERTVILLE",
      "state": "AL",
      "beds": 0,
      "baths": 2,
      "sqft": 1770,
      "lotSize": 0.3484848,
      "lat": 34.2496245,
      "lng": -86.2065491,
      "entity": "SIMPSON PROPERTY LLC"
    },
    {
      "propertyId": null,
      "attomId": 290534771,
      "offerDate": "2025-01-15T06:00:00.000Z",
      "offerPrice": 70000,
      "status": "recorded",
      "isRebuilt": false,
      "address": "1605 SANDERS AVE NE, FORT PAYNE AL",
      "city": "FORT PAYNE",
      "state": "AL",
      "beds": 0,
      "baths": 1,
      "sqft": 886,
      "lotSize": 0,
      "lat": 34.4386077,
      "lng": -85.7215731,
      "entity": "SIMPSON PROPERTY LLC"
    },
    {
      "propertyId": null,
      "attomId": 290534771,
      "offerDate": "2025-01-15T06:00:00.000Z",
      "offerPrice": 70000,
      "status": "recorded",
      "isRebuilt": false,
      "address": "1605 SANDERS AVE NE, FORT PAYNE AL",
      "city": "FORT PAYNE",
      "state": "AL",
      "beds": 0,
      "baths": 1,
      "sqft": 886,
      "lotSize": 0,
      "lat": 34.4386077,
      "lng": -85.7215731,
      "entity": "SIMPSON PROPERTY LLC"
    },
    {
      "propertyId": null,
      "attomId": 290531459,
      "offerDate": "2025-01-06T06:00:00.000Z",
      "offerPrice": 65000,
      "status": "recorded",
      "isRebuilt": false,
      "address": "63 VERNON ST, FYFFE AL",
      "city": "FYFFE",
      "state": "AL",
      "beds": 0,
      "baths": 1,
      "sqft": 1248,
      "lotSize": 1,
      "lat": 53.5610237,
      "lng": -113.8792243,
      "entity": "SIMPSON PROPERTY LLC"
    },
    {
      "propertyId": null,
      "attomId": 290531459,
      "offerDate": "2025-01-06T06:00:00.000Z",
      "offerPrice": 65000,
      "status": "recorded",
      "isRebuilt": false,
      "address": "63 VERNON ST, FYFFE AL",
      "city": "FYFFE",
      "state": "AL",
      "beds": 0,
      "baths": 1,
      "sqft": 1248,
      "lotSize": 1,
      "lat": 53.5610237,
      "lng": -113.8792243,
      "entity": "SIMPSON PROPERTY LLC"
    }
  ]
}